define.v

// ALU_Ctrl
`define ALU_NONE                                4'b0000
`define ALU_SHIFTL                              4'b0001
`define ALU_SHIFTR                              4'b0010
`define ALU_SHIFTR_ARITH                        4'b0011
`define ALU_ADD                                 4'b0100
`define ALU_SUB                                 4'b0110
`define ALU_AND                                 4'b0111
`define ALU_OR                                  4'b1000
`define ALU_XOR                                 4'b1001
`define ALU_LESS_THAN                           4'b1010
`define ALU_LESS_THAN_SIGNED                    4'b1011


// sel_ext
`define Ext_ImmI      3'b000 // Immediate extension for I-type instructions
`define Ext_ImmS      3'b001
`define Ext_ImmB      3'b010
`define Ext_ImmU      3'b011
`define Ext_ImmJ      3'b100


//ALUOP
`define ALUOP_LOAD_STORE                        3'b000
`define ALUOP_RTYPE                             3'b001
`define ALUOP_ITYPE                            3'b010
`define ALUOP_BRANCH                            3'b011
`define ALUOP_J_UAL                          3'b100

//ResultSrc
`define FROM_ALU                                 3'b000          // from ALU Result
`define FROM_MEM                                 3'b001          // from Memory
`define FROM_PC_                                 3'b010          // PC + 4
`define FROM_IMM                                 3'b011          // ImmExt

// Opcode definitions
`define OPCODE_RTYPE  7'b011_0011  // R-type
`define OPCODE_ITYPE  7'b001_0011  // I-type 
`define OPCODE_LOAD   7'b000_0011  // lw
`define OPCODE_STORE  7'b010_0011  // sw
`define OPCODE_BRANCH 7'b110_0011  // B-Type(beq)
`define OPCODE_JAL    7'b110_1111  // J-Type(jal)
`define OPCODE_LUI    7'b011_0111  // U-Type(lui)

// sel_ext
`define ALU_IMM 1'b1 // the second ALU operand is immediate
`define ALU_REG 1'b0 // the second ALU operand is register


// PCSrc
`define PC_NOJUMP 1'b0 // PC + 4
`define PC_J_OFFSET 1'b1 // PC + immediate offset


//YES/NO
`define YES 1'b1
`define NO  1'b0

src/ALU.v
`include "defines.v"

module ALU(A, B, ALUControl, Result, Zero);
   input  signed [31:0] A, B;
   input         [3:0]  ALUControl;  
   output Zero;  
   
   reg [31:0] Result;
       
   always @(*) begin
      case (ALUControl)
      `ALU_ADD: Result = A + B;
      `ALU_SUB: Result = A - B; 
      `ALU_XOR: Result = A ^ B;
      `ALU_OR:  Result = A | B;
      `ALU_AND: Result = A & B;
      `ALU_SHIFTL: Result = A << B[4:0]; 
      `ALU_SHIFTR: Result = A >> B[4:0];  
      `ALU_SHIFTR_ARITH: Result = A >>> B[4:0];  
      `ALU_LESS_THAN_SIGNED: Result = ($signed(A) < $signed(B)) ? 32'b1 : 32'b0;  // SLT
      `ALU_LESS_THAN: Result = ($unsigned(A) < $unsigned(B)) ? 32'b1 : 32'b0;  // SLTU
      
      `ALU_NONE: Result = A;  // Pass through A
      default: Result = A;
      endcase
   end 
   
   assign Zero = (Result == 32'b0);  

endmodule

testbench/ALU_tb.v
`timescale 1ns / 1ps
`include "define.v"

module ALU_tb;

    // Testbench signals
    reg signed [31:0] A, B;
    reg [3:0] ALUControl;
    wire [31:0] Result;
    wire Zero;
    
    // Test tracking
    reg test_passed;
    integer test_count;
    
    // Expected results for comparison
    reg [31:0] expected_result;
    reg expected_zero;
    
    // Instantiate the ALU
    ALU uut (
        .A(A),
        .B(B),
        .ALUControl(ALUControl),
        .Result(Result),
        .Zero(Zero)
    );
    
    // VCD dump
    initial begin
        $dumpfile("ALU_tb.vcd");
        $dumpvars(0, ALU_tb);
    end
    
    // Test sequence
    initial begin
        $display("=== ALU Module Testbench ===");
        $display("Time\tALUCtrl\tA\t\tB\t\tResult\t\tZero\tExpected\tTest Description");
        
        test_passed = 1;
        test_count = 0;
        
        // Initialize signals
        A = 0;
        B = 0;
        ALUControl = `ALU_NONE;
        #10;
        
        $display("\n--- Test 1: ALU_ADD (Addition) ---");
        
        // Test 1.1: Positive + Positive
        A = 32'h12345678; B = 32'h87654321; ALUControl = `ALU_ADD;
        expected_result = 32'h12345678 + 32'h87654321;
        expected_zero = (expected_result == 0);
        #10;
        $display("%0t\t%b\t%08x\t%08x\t%08x\t%b\t%08x\t%s", 
                 $time, ALUControl, A, B, Result, Zero, expected_result, "ADD: pos+pos");
        
        if (Result == expected_result && Zero == expected_zero) begin
            $display("✓ PASS: Addition positive numbers");
        end else begin
            $display("✗ FAIL: Expected Result=%08x Zero=%b, got Result=%08x Zero=%b", 
                     expected_result, expected_zero, Result, Zero);
            test_passed = 0;
        end
        test_count = test_count + 1;
        
        // Test 1.2: Addition resulting in zero
        A = 32'hFFFFFFFF; B = 32'h00000001; ALUControl = `ALU_ADD;
        expected_result = 32'h00000000;
        expected_zero = 1;
        #10;
        $display("%0t\t%b\t%08x\t%08x\t%08x\t%b\t%08x\t%s", 
                 $time, ALUControl, A, B, Result, Zero, expected_result, "ADD: -1+1=0");
        
        if (Result == expected_result && Zero == expected_zero) begin
            $display("✓ PASS: Addition zero result");
        end else begin
            $display("✗ FAIL: Expected Result=%08x Zero=%b, got Result=%08x Zero=%b", 
                     expected_result, expected_zero, Result, Zero);
            test_passed = 0;
        end
        test_count = test_count + 1;
        
        $display("\n--- Test 2: ALU_SUB (Subtraction) ---");
        
        // Test 2.1: Basic subtraction
        A = 32'h87654321; B = 32'h12345678; ALUControl = `ALU_SUB;
        expected_result = 32'h87654321 - 32'h12345678;
        expected_zero = (expected_result == 0);
        #10;
        $display("%0t\t%b\t%08x\t%08x\t%08x\t%b\t%08x\t%s", 
                 $time, ALUControl, A, B, Result, Zero, expected_result, "SUB: basic");
        
        if (Result == expected_result && Zero == expected_zero) begin
            $display("✓ PASS: Subtraction basic");
        end else begin
            $display("✗ FAIL: Expected Result=%08x Zero=%b, got Result=%08x Zero=%b", 
                     expected_result, expected_zero, Result, Zero);
            test_passed = 0;
        end
        test_count = test_count + 1;
        
        // Test 2.2: Subtraction resulting in zero
        A = 32'h12345678; B = 32'h12345678; ALUControl = `ALU_SUB;
        expected_result = 32'h00000000;
        expected_zero = 1;
        #10;
        $display("%0t\t%b\t%08x\t%08x\t%08x\t%b\t%08x\t%s", 
                 $time, ALUControl, A, B, Result, Zero, expected_result, "SUB: same=0");
        
        if (Result == expected_result && Zero == expected_zero) begin
            $display("✓ PASS: Subtraction zero result");
        end else begin
            $display("✗ FAIL: Expected Result=%08x Zero=%b, got Result=%08x Zero=%b", 
                     expected_result, expected_zero, Result, Zero);
            test_passed = 0;
        end
        test_count = test_count + 1;
        
        $display("\n--- Test 3: ALU_AND (Bitwise AND) ---");
        
        A = 32'hF0F0F0F0; B = 32'h0F0F0F0F; ALUControl = `ALU_AND;
        expected_result = 32'h00000000;
        expected_zero = 1;
        #10;
        $display("%0t\t%b\t%08x\t%08x\t%08x\t%b\t%08x\t%s", 
                 $time, ALUControl, A, B, Result, Zero, expected_result, "AND: no overlap");
        
        if (Result == expected_result && Zero == expected_zero) begin
            $display("✓ PASS: AND no overlap");
        end else begin
            $display("✗ FAIL: Expected Result=%08x Zero=%b, got Result=%08x Zero=%b", 
                     expected_result, expected_zero, Result, Zero);
            test_passed = 0;
        end
        test_count = test_count + 1;
        
        // AND with overlap
        A = 32'hFFFF0000; B = 32'h0000FFFF; ALUControl = `ALU_AND;
        expected_result = 32'h00000000;
        expected_zero = 1;
        #10;
        A = 32'hFFFFFFFF; B = 32'h12345678; ALUControl = `ALU_AND;
        expected_result = 32'h12345678;
        expected_zero = 0;
        #10;
        $display("%0t\t%b\t%08x\t%08x\t%08x\t%b\t%08x\t%s", 
                 $time, ALUControl, A, B, Result, Zero, expected_result, "AND: all 1s");
        
        if (Result == expected_result && Zero == expected_zero) begin
            $display("✓ PASS: AND with all 1s");
        end else begin
            $display("✗ FAIL: Expected Result=%08x Zero=%b, got Result=%08x Zero=%b", 
                     expected_result, expected_zero, Result, Zero);
            test_passed = 0;
        end
        test_count = test_count + 1;
        
        $display("\n--- Test 4: ALU_OR (Bitwise OR) ---");
        
        A = 32'hF0F0F0F0; B = 32'h0F0F0F0F; ALUControl = `ALU_OR;
        expected_result = 32'hFFFFFFFF;
        expected_zero = 0;
        #10;
        $display("%0t\t%b\t%08x\t%08x\t%08x\t%b\t%08x\t%s", 
                 $time, ALUControl, A, B, Result, Zero, expected_result, "OR: complement");
        
        if (Result == expected_result && Zero == expected_zero) begin
            $display("✓ PASS: OR complement patterns");
        end else begin
            $display("✗ FAIL: Expected Result=%08x Zero=%b, got Result=%08x Zero=%b", 
                     expected_result, expected_zero, Result, Zero);
            test_passed = 0;
        end
        test_count = test_count + 1;
        
        // OR with zero
        A = 32'h00000000; B = 32'h00000000; ALUControl = `ALU_OR;
        expected_result = 32'h00000000;
        expected_zero = 1;
        #10;
        $display("%0t\t%b\t%08x\t%08x\t%08x\t%b\t%08x\t%s", 
                 $time, ALUControl, A, B, Result, Zero, expected_result, "OR: zero");
        
        if (Result == expected_result && Zero == expected_zero) begin
            $display("✓ PASS: OR with zeros");
        end else begin
            $display("✗ FAIL: Expected Result=%08x Zero=%b, got Result=%08x Zero=%b", 
                     expected_result, expected_zero, Result, Zero);
            test_passed = 0;
        end
        test_count = test_count + 1;
        
        $display("\n--- Test 5: ALU_XOR (Bitwise XOR) ---");
        
        A = 32'hAAAAAAAA; B = 32'h55555555; ALUControl = `ALU_XOR;
        expected_result = 32'hFFFFFFFF;
        expected_zero = 0;
        #10;
        $display("%0t\t%b\t%08x\t%08x\t%08x\t%b\t%08x\t%s", 
                 $time, ALUControl, A, B, Result, Zero, expected_result, "XOR: invert");
        
        if (Result == expected_result && Zero == expected_zero) begin
            $display("✓ PASS: XOR inverting pattern");
        end else begin
            $display("✗ FAIL: Expected Result=%08x Zero=%b, got Result=%08x Zero=%b", 
                     expected_result, expected_zero, Result, Zero);
            test_passed = 0;
        end
        test_count = test_count + 1;
        
        // XOR same values (should be zero)
        A = 32'h12345678; B = 32'h12345678; ALUControl = `ALU_XOR;
        expected_result = 32'h00000000;
        expected_zero = 1;
        #10;
        $display("%0t\t%b\t%08x\t%08x\t%08x\t%b\t%08x\t%s", 
                 $time, ALUControl, A, B, Result, Zero, expected_result, "XOR: same=0");
        
        if (Result == expected_result && Zero == expected_zero) begin
            $display("✓ PASS: XOR same values");
        end else begin
            $display("✗ FAIL: Expected Result=%08x Zero=%b, got Result=%08x Zero=%b", 
                     expected_result, expected_zero, Result, Zero);
            test_passed = 0;
        end
        test_count = test_count + 1;
        
        $display("\n--- Test 6: ALU_SHIFTL (Shift Left) ---");
        
        A = 32'h00000001; B = 32'h00000004; ALUControl = `ALU_SHIFTL;
        expected_result = 32'h00000010;
        expected_zero = 0;
        #10;
        $display("%0t\t%b\t%08x\t%08x\t%08x\t%b\t%08x\t%s", 
                 $time, ALUControl, A, B, Result, Zero, expected_result, "SLL: 1<<4");
        
        if (Result == expected_result && Zero == expected_zero) begin
            $display("✓ PASS: Shift left basic");
        end else begin
            $display("✗ FAIL: Expected Result=%08x Zero=%b, got Result=%08x Zero=%b", 
                     expected_result, expected_zero, Result, Zero);
            test_passed = 0;
        end
        test_count = test_count + 1;
        
        // Shift left with overflow
        A = 32'hF0000000; B = 32'h00000004; ALUControl = `ALU_SHIFTL;
        expected_result = 32'h00000000;
        expected_zero = 1;
        #10;
        $display("%0t\t%b\t%08x\t%08x\t%08x\t%b\t%08x\t%s", 
                 $time, ALUControl, A, B, Result, Zero, expected_result, "SLL: overflow");
        
        if (Result == expected_result && Zero == expected_zero) begin
            $display("✓ PASS: Shift left overflow");
        end else begin
            $display("✗ FAIL: Expected Result=%08x Zero=%b, got Result=%08x Zero=%b", 
                     expected_result, expected_zero, Result, Zero);
            test_passed = 0;
        end
        test_count = test_count + 1;
        
        $display("\n--- Test 7: ALU_SHIFTR (Shift Right Logical) ---");
        
        A = 32'h80000000; B = 32'h00000004; ALUControl = `ALU_SHIFTR;
        expected_result = 32'h08000000;
        expected_zero = 0;
        #10;
        $display("%0t\t%b\t%08x\t%08x\t%08x\t%b\t%08x\t%s", 
                 $time, ALUControl, A, B, Result, Zero, expected_result, "SRL: logical");
        
        if (Result == expected_result && Zero == expected_zero) begin
            $display("✓ PASS: Shift right logical");
        end else begin
            $display("✗ FAIL: Expected Result=%08x Zero=%b, got Result=%08x Zero=%b", 
                     expected_result, expected_zero, Result, Zero);
            test_passed = 0;
        end
        test_count = test_count + 1;
        
        $display("\n--- Test 8: ALU_SHIFTR_ARITH (Shift Right Arithmetic) ---");
        
        A = 32'h80000000; B = 32'h00000004; ALUControl = `ALU_SHIFTR_ARITH;
        expected_result = 32'hF8000000; // Sign extension
        expected_zero = 0;
        #10;
        $display("%0t\t%b\t%08x\t%08x\t%08x\t%b\t%08x\t%s", 
                 $time, ALUControl, A, B, Result, Zero, expected_result, "SRA: negative");
        
        if (Result == expected_result && Zero == expected_zero) begin
            $display("✓ PASS: Shift right arithmetic negative");
        end else begin
            $display("✗ FAIL: Expected Result=%08x Zero=%b, got Result=%08x Zero=%b", 
                     expected_result, expected_zero, Result, Zero);
            test_passed = 0;
        end
        test_count = test_count + 1;
        
        // Positive number arithmetic shift
        A = 32'h70000000; B = 32'h00000004; ALUControl = `ALU_SHIFTR_ARITH;
        expected_result = 32'h07000000;
        expected_zero = 0;
        #10;
        $display("%0t\t%b\t%08x\t%08x\t%08x\t%b\t%08x\t%s", 
                 $time, ALUControl, A, B, Result, Zero, expected_result, "SRA: positive");
        
        if (Result == expected_result && Zero == expected_zero) begin
            $display("✓ PASS: Shift right arithmetic positive");
        end else begin
            $display("✗ FAIL: Expected Result=%08x Zero=%b, got Result=%08x Zero=%b", 
                     expected_result, expected_zero, Result, Zero);
            test_passed = 0;
        end
        test_count = test_count + 1;
        
        $display("\n--- Test 9: ALU_LESS_THAN_SIGNED (SLT) ---");
        
        // Test signed comparison: -1 < 1
        A = 32'hFFFFFFFF; B = 32'h00000001; ALUControl = `ALU_LESS_THAN_SIGNED;
        expected_result = 32'h00000001;
        expected_zero = 0;
        #10;
        $display("%0t\t%b\t%08x\t%08x\t%08x\t%b\t%08x\t%s", 
                 $time, ALUControl, A, B, Result, Zero, expected_result, "SLT: -1<1");
        
        if (Result == expected_result && Zero == expected_zero) begin
            $display("✓ PASS: SLT negative less than positive");
        end else begin
            $display("✗ FAIL: Expected Result=%08x Zero=%b, got Result=%08x Zero=%b", 
                     expected_result, expected_zero, Result, Zero);
            test_passed = 0;
        end
        test_count = test_count + 1;
        
        // Test signed comparison: 1 < -1 (false)
        A = 32'h00000001; B = 32'hFFFFFFFF; ALUControl = `ALU_LESS_THAN_SIGNED;
        expected_result = 32'h00000000;
        expected_zero = 1;
        #10;
        $display("%0t\t%b\t%08x\t%08x\t%08x\t%b\t%08x\t%s", 
                 $time, ALUControl, A, B, Result, Zero, expected_result, "SLT: 1<-1");
        
        if (Result == expected_result && Zero == expected_zero) begin
            $display("✓ PASS: SLT positive not less than negative");
        end else begin
            $display("✗ FAIL: Expected Result=%08x Zero=%b, got Result=%08x Zero=%b", 
                     expected_result, expected_zero, Result, Zero);
            test_passed = 0;
        end
        test_count = test_count + 1;
        
        $display("\n--- Test 10: ALU_LESS_THAN (SLTU) ---");
        
        // Test unsigned comparison: 0xFFFFFFFF > 0x00000001 
        A = 32'hFFFFFFFF; B = 32'h00000001; ALUControl = `ALU_LESS_THAN;
        expected_result = 32'h00000000;
        expected_zero = 1;
        #10;
        $display("%0t\t%b\t%08x\t%08x\t%08x\t%b\t%08x\t%s", 
                 $time, ALUControl, A, B, Result, Zero, expected_result, "SLTU: large>small");
        
        if (Result == expected_result && Zero == expected_zero) begin
            $display("✓ PASS: SLTU large unsigned not less than small");
        end else begin
            $display("✗ FAIL: Expected Result=%08x Zero=%b, got Result=%08x Zero=%b", 
                     expected_result, expected_zero, Result, Zero);
            test_passed = 0;
        end
        test_count = test_count + 1;
        
        // Test unsigned comparison: 0x00000001 < 0xFFFFFFFF
        A = 32'h00000001; B = 32'hFFFFFFFF; ALUControl = `ALU_LESS_THAN;
        expected_result = 32'h00000001;
        expected_zero = 0;
        #10;
        $display("%0t\t%b\t%08x\t%08x\t%08x\t%b\t%08x\t%s", 
                 $time, ALUControl, A, B, Result, Zero, expected_result, "SLTU: small<large");
        
        if (Result == expected_result && Zero == expected_zero) begin
            $display("✓ PASS: SLTU small unsigned less than large");
        end else begin
            $display("✗ FAIL: Expected Result=%08x Zero=%b, got Result=%08x Zero=%b", 
                     expected_result, expected_zero, Result, Zero);
            test_passed = 0;
        end
        test_count = test_count + 1;
        
        $display("\n--- Test 11: ALU_NONE (Pass Through) ---");
        
        A = 32'h12345678; B = 32'h87654321; ALUControl = `ALU_NONE;
        expected_result = 32'h12345678; // Should pass A through
        expected_zero = 0;
        #10;
        $display("%0t\t%b\t%08x\t%08x\t%08x\t%b\t%08x\t%s", 
                 $time, ALUControl, A, B, Result, Zero, expected_result, "NONE: pass A");
        
        if (Result == expected_result && Zero == expected_zero) begin
            $display("✓ PASS: ALU_NONE passes A through");
        end else begin
            $display("✗ FAIL: Expected Result=%08x Zero=%b, got Result=%08x Zero=%b", 
                     expected_result, expected_zero, Result, Zero);
            test_passed = 0;
        end
        test_count = test_count + 1;
        
        // Test ALU_NONE with zero
        A = 32'h00000000; B = 32'h12345678; ALUControl = `ALU_NONE;
        expected_result = 32'h00000000;
        expected_zero = 1;
        #10;
        $display("%0t\t%b\t%08x\t%08x\t%08x\t%b\t%08x\t%s", 
                 $time, ALUControl, A, B, Result, Zero, expected_result, "NONE: pass 0");
        
        if (Result == expected_result && Zero == expected_zero) begin
            $display("✓ PASS: ALU_NONE passes zero through");
        end else begin
            $display("✗ FAIL: Expected Result=%08x Zero=%b, got Result=%08x Zero=%b", 
                     expected_result, expected_zero, Result, Zero);
            test_passed = 0;
        end
        test_count = test_count + 1;
        
        $display("\n--- Test 12: Invalid ALU Control (Default Case) ---");
        
        A = 32'h12345678; B = 32'h87654321; ALUControl = 4'b1111; // Invalid control
        expected_result = 32'h12345678; // Should default to passing A
        expected_zero = 0;
        #10;
        $display("%0t\t%b\t%08x\t%08x\t%08x\t%b\t%08x\t%s", 
                 $time, ALUControl, A, B, Result, Zero, expected_result, "Invalid: default");
        
        if (Result == expected_result && Zero == expected_zero) begin
            $display("✓ PASS: Invalid control defaults to pass A");
        end else begin
            $display("✗ FAIL: Expected Result=%08x Zero=%b, got Result=%08x Zero=%b", 
                     expected_result, expected_zero, Result, Zero);
            test_passed = 0;
        end
        test_count = test_count + 1;
        
        $display("\n--- Test 13: Edge Cases ---");
        
        // Test maximum positive + 1 (overflow)
        A = 32'h7FFFFFFF; B = 32'h00000001; ALUControl = `ALU_ADD;
        expected_result = 32'h80000000; // Overflow to negative
        expected_zero = 0;
        #10;
        $display("%0t\t%b\t%08x\t%08x\t%08x\t%b\t%08x\t%s", 
                 $time, ALUControl, A, B, Result, Zero, expected_result, "ADD: overflow");
        
        if (Result == expected_result && Zero == expected_zero) begin
            $display("✓ PASS: Addition overflow behavior");
        end else begin
            $display("✗ FAIL: Expected Result=%08x Zero=%b, got Result=%08x Zero=%b", 
                     expected_result, expected_zero, Result, Zero);
            test_passed = 0;
        end
        test_count = test_count + 1;
        
        // Test shift by 0
        A = 32'h12345678; B = 32'h00000000; ALUControl = `ALU_SHIFTL;
        expected_result = 32'h12345678; // No shift
        expected_zero = 0;
        #10;
        $display("%0t\t%b\t%08x\t%08x\t%08x\t%b\t%08x\t%s", 
                 $time, ALUControl, A, B, Result, Zero, expected_result, "SLL: shift 0");
        
        if (Result == expected_result && Zero == expected_zero) begin
            $display("✓ PASS: Shift by zero");
        end else begin
            $display("✗ FAIL: Expected Result=%08x Zero=%b, got Result=%08x Zero=%b", 
                     expected_result, expected_zero, Result, Zero);
            test_passed = 0;
        end
        test_count = test_count + 1;
        
        // Final results
        $display("\n=== ALU Testbench Complete ===");
        if (test_passed) begin
            $display("🎉 ALL TESTS PASSED! (%0d/%0d)", test_count, test_count);
        end else begin
            $display("❌ SOME TESTS FAILED!");
        end
        
        #50;
        $finish;
    end

endmodule

testbench/ALU_tb.vcd
$date
	Mon Dec 15 15:11:50 2025
$end
$version
	Icarus Verilog
$end
$timescale
	1ps
$end
$scope module ALU_tb $end
$var wire 1 ! Zero $end
$var wire 32 " Result [31:0] $end
$var reg 32 # A [31:0] $end
$var reg 4 $ ALUControl [3:0] $end
$var reg 32 % B [31:0] $end
$var reg 32 & expected_result [31:0] $end
$var reg 1 ' expected_zero $end
$var reg 1 ( test_passed $end
$var integer 32 ) test_count [31:0] $end
$scope module uut $end
$var wire 32 * A [31:0] $end
$var wire 4 + ALUControl [3:0] $end
$var wire 32 , B [31:0] $end
$var wire 1 ! Zero $end
$var reg 32 - Result [31:0] $end
$upscope $end
$upscope $end
$enddefinitions $end
$comment Show the parameter values. $end
$dumpall
$end
#0
$dumpvars
b0 -
b0 ,
b0 +
b0 *
b0 )
1(
x'
bx &
b0 %
b0 $
b0 #
b0 "
1!
$end
#10000
0!
b10011001100110011001100110011001 "
b10011001100110011001100110011001 -
0'
b10011001100110011001100110011001 &
b100 $
b100 +
b10000111011001010100001100100001 %
b10000111011001010100001100100001 ,
b10010001101000101011001111000 #
b10010001101000101011001111000 *
#20000
1!
b0 "
b0 -
1'
b0 &
b1 %
b1 ,
b11111111111111111111111111111111 #
b11111111111111111111111111111111 *
b1 )
#30000
0!
b1110101001100001110110010101001 "
b1110101001100001110110010101001 -
0'
b1110101001100001110110010101001 &
b110 $
b110 +
b10010001101000101011001111000 %
b10010001101000101011001111000 ,
b10000111011001010100001100100001 #
b10000111011001010100001100100001 *
b10 )
#40000
1!
b0 "
b0 -
1'
b0 &
b10010001101000101011001111000 #
b10010001101000101011001111000 *
b11 )
#50000
b111 $
b111 +
b1111000011110000111100001111 %
b1111000011110000111100001111 ,
b11110000111100001111000011110000 #
b11110000111100001111000011110000 *
b100 )
#60000
0!
b10010001101000101011001111000 "
b10010001101000101011001111000 -
0'
b10010001101000101011001111000 &
b10010001101000101011001111000 %
b10010001101000101011001111000 ,
b11111111111111111111111111111111 #
b11111111111111111111111111111111 *
b101 )
#70000
b11111111111111111111111111111111 "
b11111111111111111111111111111111 -
b11111111111111111111111111111111 &
b1000 $
b1000 +
b1111000011110000111100001111 %
b1111000011110000111100001111 ,
b11110000111100001111000011110000 #
b11110000111100001111000011110000 *
b110 )
#80000
1!
b0 "
b0 -
1'
b0 &
b0 %
b0 ,
b0 #
b0 *
b111 )
#90000
0!
b11111111111111111111111111111111 "
b11111111111111111111111111111111 -
0'
b11111111111111111111111111111111 &
b1001 $
b1001 +
b1010101010101010101010101010101 %
b1010101010101010101010101010101 ,
b10101010101010101010101010101010 #
b10101010101010101010101010101010 *
b1000 )
#100000
1!
b0 "
b0 -
1'
b0 &
b10010001101000101011001111000 %
b10010001101000101011001111000 ,
b10010001101000101011001111000 #
b10010001101000101011001111000 *
b1001 )
#110000
0!
b10000 "
b10000 -
0'
b10000 &
b1 $
b1 +
b100 %
b100 ,
b1 #
b1 *
b1010 )
#120000
b11110000000000000000000000000000 "
b11110000000000000000000000000000 -
b11110000000000000000000000000000 &
b1000000 %
b1000000 ,
b11110000000000000000000000000000 #
b11110000000000000000000000000000 *
b1011 )
#130000
b1000000000000000000000000000 "
b1000000000000000000000000000 -
b1000000000000000000000000000 &
b10 $
b10 +
b100 %
b100 ,
b10000000000000000000000000000000 #
b10000000000000000000000000000000 *
b1100 )
#140000
b11111000000000000000000000000000 "
b11111000000000000000000000000000 -
b11111000000000000000000000000000 &
b11 $
b11 +
b1101 )
#150000
b111000000000000000000000000 "
b111000000000000000000000000 -
b111000000000000000000000000 &
b1110000000000000000000000000000 #
b1110000000000000000000000000000 *
b1110 )
#160000
b1 "
b1 -
b1 &
b1011 $
b1011 +
b1 %
b1 ,
b11111111111111111111111111111111 #
b11111111111111111111111111111111 *
b1111 )
#170000
1!
b0 "
b0 -
1'
b0 &
b11111111111111111111111111111111 %
b11111111111111111111111111111111 ,
b1 #
b1 *
b10000 )
#180000
b1010 $
b1010 +
b1 %
b1 ,
b11111111111111111111111111111111 #
b11111111111111111111111111111111 *
b10001 )
#190000
0!
b1 "
b1 -
0'
b1 &
b11111111111111111111111111111111 %
b11111111111111111111111111111111 ,
b1 #
b1 *
b10010 )
#200000
b10010001101000101011001111000 "
b10010001101000101011001111000 -
b10010001101000101011001111000 &
b0 $
b0 +
b10000111011001010100001100100001 %
b10000111011001010100001100100001 ,
b10010001101000101011001111000 #
b10010001101000101011001111000 *
b10011 )
#210000
1!
b0 "
b0 -
1'
b0 &
b10010001101000101011001111000 %
b10010001101000101011001111000 ,
b0 #
b0 *
b10100 )
#220000
0!
b10010001101000101011001111000 "
b10010001101000101011001111000 -
0'
b10010001101000101011001111000 &
b1111 $
b1111 +
b10000111011001010100001100100001 %
b10000111011001010100001100100001 ,
b10010001101000101011001111000 #
b10010001101000101011001111000 *
b10101 )
#230000
b10000000000000000000000000000000 "
b10000000000000000000000000000000 -
b10000000000000000000000000000000 &
b100 $
b100 +
b1 %
b1 ,
b1111111111111111111111111111111 #
b1111111111111111111111111111111 *
b10110 )
#240000
b10010001101000101011001111000 "
b10010001101000101011001111000 -
b10010001101000101011001111000 &
b1 $
b1 +
b0 %
b0 ,
b10010001101000101011001111000 #
b10010001101000101011001111000 *
b10111 )
#250000
b11000 )
