define.v

// ALU_Ctrl
`define ALU_NONE                                4'b0000
`define ALU_SHIFTL                              4'b0001
`define ALU_SHIFTR                              4'b0010
`define ALU_SHIFTR_ARITH                        4'b0011
`define ALU_ADD                                 4'b0100
`define ALU_SUB                                 4'b0110
`define ALU_AND                                 4'b0111
`define ALU_OR                                  4'b1000
`define ALU_XOR                                 4'b1001
`define ALU_LESS_THAN                           4'b1010
`define ALU_LESS_THAN_SIGNED                    4'b1011


// sel_ext
`define Ext_ImmI      3'b000 // Immediate extension for I-type instructions
`define Ext_ImmS      3'b001
`define Ext_ImmB      3'b010
`define Ext_ImmU      3'b011
`define Ext_ImmJ      3'b100


//ALUOP
`define ALUOP_LOAD_STORE                        3'b000
`define ALUOP_RTYPE                             3'b001
`define ALUOP_ITYPE                            3'b010
`define ALUOP_BRANCH                            3'b011
`define ALUOP_J_UAL                          3'b100

//ResultSrc
`define FROM_ALU                                 3'b000          // from ALU Result
`define FROM_MEM                                 3'b001          // from Memory
`define FROM_PC_                                 3'b010          // PC + 4
`define FROM_IMM                                 3'b011          // ImmExt

// Opcode definitions
`define OPCODE_RTYPE  7'b011_0011  // R-type
`define OPCODE_ITYPE  7'b001_0011  // I-type 
`define OPCODE_LOAD   7'b000_0011  // lw
`define OPCODE_STORE  7'b010_0011  // sw
`define OPCODE_BRANCH 7'b110_0011  // B-Type(beq)
`define OPCODE_JAL    7'b110_1111  // J-Type(jal)
`define OPCODE_LUI    7'b011_0111  // U-Type(lui)

// sel_ext
`define ALU_IMM 1'b1 // the second ALU operand is immediate
`define ALU_REG 1'b0 // the second ALU operand is register


// PCSrc
`define PC_NOJUMP 1'b0 // PC + 4
`define PC_J_OFFSET 1'b1 // PC + immediate offset


//YES/NO
`define YES 1'b1
`define NO  1'b0

src/Data_Memory.v
module Data_Memory(clk,rst,WE,WD,A,RD);

    input clk,rst,WE;
    input [31:0]A,WD;
    output [31:0]RD;

    reg [31:0] mem [1023:0];

    always @ (posedge clk)
    begin
        if(WE)
            mem[A] <= WD;
    end

    assign RD = (~rst) ? 32'd0 : mem[A];

    // initial begin
    //     mem[28] = 32'h00000020;
    //     //mem[40] = 32'h00000002;
    // end


endmodule

testbench/Data_Memory_tb.v
`timescale 1ns / 1ps
`include "define.v"

module Data_Memory_tb;

    // Testbench signals
    reg clk;
    reg rst;
    reg WE;
    reg [31:0] A, WD;
    wire [31:0] RD;
    
    // Test tracking
    reg test_passed;
    integer test_count;
    
    // Temp variables for tests
    reg [31:0] data_addr20, data_addr30;
    
    // Instantiate the Data Memory
    Data_Memory uut (
        .clk(clk),
        .rst(rst),
        .WE(WE),
        .WD(WD),
        .A(A),
        .RD(RD)
    );
    
    // Generate clock
    always begin
        clk = 0; #5;
        clk = 1; #5;
    end
    
    // VCD dump
    initial begin
        $dumpfile("Data_Memory_tb.vcd");
        $dumpvars(0, Data_Memory_tb);
    end
    
    // Test sequence
    initial begin
        $display("=== Data Memory Module Testbench ===");
        $display("Time\tRst\tWE\tAddr\t\tWriteData\tReadData\tTest Description");
        
        test_passed = 1;
        test_count = 0;
        
        // Initialize signals
        rst = 1;
        WE = 0;
        A = 0;
        WD = 0;
        
        // Test 1: Reset functionality
        $display("\n--- Test 1: Reset Functionality ---");
        rst = 0;
        A = 32'h00000000;
        #20;
        $display("%0t\t%b\t%b\t%08x\t%08x\t%08x\tReset=0", 
                 $time, rst, WE, A, WD, RD);
        
        if (RD == 32'h0) begin
            $display("✓ PASS: Reset properly disables memory output");
        end else begin
            $display("✗ FAIL: Reset should disable output, got %08x", RD);
            test_passed = 0;
        end
        test_count = test_count + 1;
        
        rst = 1; #20; // Release reset
        
        // Test 2: Basic write operation
        $display("\n--- Test 2: Basic Write Operation ---");
        WE = 1;
        A = 32'h00000010; // Address 16
        WD = 32'h12345678;
        #20; // Wait for clock edge
        
        $display("%0t\t%b\t%b\t%08x\t%08x\t%08x\tWrite", 
                 $time, rst, WE, A, WD, RD);
        
        // Test 3: Read the written data
        $display("\n--- Test 3: Read Written Data ---");
        WE = 0; // Disable write
        #20; // Wait for read
        
        $display("%0t\t%b\t%b\t%08x\t%08x\t%08x\tRead", 
                 $time, rst, WE, A, WD, RD);
        
        if (RD == 32'h12345678) begin
            $display("✓ PASS: Basic write/read works correctly");
        end else begin
            $display("✗ FAIL: Expected %08x, got %08x", 32'h12345678, RD);
            test_passed = 0;
        end
        test_count = test_count + 1;
        
        // Test 4: Write enable control
        $display("\n--- Test 4: Write Enable Control ---");
        WE = 0; // Write disabled
        A = 32'h00000014; // Different address
        WD = 32'hDEADBEEF;
        #20;
        
        $display("%0t\t%b\t%b\t%08x\t%08x\t%08x\tWE=0 Write", 
                 $time, rst, WE, A, WD, RD);
        
        if (RD == 32'h0) begin // Should read 0 since location was never written
            $display("✓ PASS: Write disabled when WE=0");
        end else begin
            $display("⚠ INFO: Location contains %08x (might be from initialization)", RD);
        end
        test_count = test_count + 1;
        
        // Test 5: Multiple writes to different addresses
        $display("\n--- Test 5: Multiple Address Write/Read ---");
        WE = 1;
        
        // Write to address 20
        A = 32'h00000020;
        WD = 32'hABCDEF00;
        #20;
        WE = 0; #10;
        data_addr20 = RD;
        $display("%0t\t%b\t%b\t%08x\t%08x\t%08x\tAddr 20", 
                 $time, rst, WE, A, WD, RD);
        
        // Write to address 30  
        WE = 1;
        A = 32'h00000030;
        WD = 32'hCAFEBABE;
        #20;
        WE = 0; #10;
        data_addr30 = RD;
        $display("%0t\t%b\t%b\t%08x\t%08x\t%08x\tAddr 30", 
                 $time, rst, WE, A, WD, RD);
        
        // Verify independence - read back addr 20
        A = 32'h00000020; #10;
        $display("%0t\t%b\t%b\t%08x\t%08x\t%08x\tReread 20", 
                 $time, rst, WE, A, WD, RD);
        
        if (RD == data_addr20 && data_addr20 == 32'hABCDEF00) begin
            $display("✓ PASS: Multiple addresses work independently");
        end else begin
            $display("✗ FAIL: Address independence failed. Expected %08x, got %08x", 
                     32'hABCDEF00, RD);
            test_passed = 0;
        end
        test_count = test_count + 1;
        
        // Test 6: Data overwrite
        $display("\n--- Test 6: Data Overwrite ---");
        WE = 1;
        A = 32'h00000010; // Same address as Test 2
        WD = 32'hFFFFFFFF; // New data
        #20;
        WE = 0; #10;
        
        $display("%0t\t%b\t%b\t%08x\t%08x\t%08x\tOverwrite", 
                 $time, rst, WE, A, WD, RD);
        
        if (RD == 32'hFFFFFFFF) begin
            $display("✓ PASS: Data overwrite works correctly");
        end else begin
            $display("✗ FAIL: Overwrite failed. Expected FFFFFFFF, got %08x", RD);
            test_passed = 0;
        end
        test_count = test_count + 1;
        
        // Test 7: Boundary addresses
        $display("\n--- Test 7: Boundary Address Access ---");
        
        // Test address 0
        WE = 1;
        A = 32'h00000000;
        WD = 32'h00000001;
        #20;
        WE = 0; #10;
        $display("%0t\t%b\t%b\t%08x\t%08x\t%08x\tAddr 0", 
                 $time, rst, WE, A, WD, RD);
        
        if (RD == 32'h00000001) begin
            $display("✓ PASS: Address 0 works correctly");
        end else begin
            $display("✗ FAIL: Address 0 failed. Expected 00000001, got %08x", RD);
            test_passed = 0;
        end
        
        // Test large address (within bounds: mem[1023])
        WE = 1;
        A = 32'h000003FF; // Address 1023
        WD = 32'h1023ABCD;
        #20;
        WE = 0; #10;
        $display("%0t\t%b\t%b\t%08x\t%08x\t%08x\tAddr 1023", 
                 $time, rst, WE, A, WD, RD);
        
        if (RD == 32'h1023ABCD) begin
            $display("✓ PASS: Large valid address works correctly");
        end else begin
            $display("✗ FAIL: Large address failed. Expected 1023ABCD, got %08x", RD);
            test_passed = 0;
        end
        test_count = test_count + 1;
        
        // Test 8: Rapid read/write operations
        $display("\n--- Test 8: Rapid Operations ---");
        
        A = 32'h00000100;
        WE = 1;
        WD = 32'h11111111; #20;
        WE = 0; #10;
        
        if (RD == 32'h11111111) 
            $display("✓ PASS: Rapid operation 1 successful");
        
        A = 32'h00000104; 
        WE = 1;
        WD = 32'h22222222; #20;
        WE = 0; #10;
        
        if (RD == 32'h22222222) 
            $display("✓ PASS: Rapid operation 2 successful");
        
        test_count = test_count + 1;
        
        // Test 9: Write during reset
        $display("\n--- Test 9: Reset During Write ---");
        
        A = 32'h00000200;
        WD = 32'hBADBAD00;
        WE = 1;
        rst = 0; // Reset during write setup
        #20;
        rst = 1; // Release reset
        WE = 0;
        #10;
        
        $display("%0t\t%b\t%b\t%08x\t%08x\t%08x\tReset+Write", 
                 $time, rst, WE, A, WD, RD);
        
        // Memory content is undefined during reset, but output should be 0
        $display("✓ INFO: Reset behavior during write tested");
        test_count = test_count + 1;
        
        // Test 10: Clock edge behavior
        $display("\n--- Test 10: Clock Edge Timing ---");
        
        WE = 1;
        A = 32'h00000300;
        WD = 32'hCCCCCCCC;
        
        // Write should happen on positive edge
        @(posedge clk);
        #1; // Small delay after clock edge
        WE = 0;
        #5;
        
        $display("%0t\t%b\t%b\t%08x\t%08x\t%08x\tClock Edge", 
                 $time, rst, WE, A, WD, RD);
        
        if (RD == 32'hCCCCCCCC) begin
            $display("✓ PASS: Write occurs on positive clock edge");
        end else begin
            $display("✗ FAIL: Clock edge timing issue. Expected CCCCCCCC, got %08x", RD);
            test_passed = 0;
        end
        test_count = test_count + 1;
        
        // Final results
        $display("\n=== Data_Memory Testbench Complete ===");
        if (test_passed) begin
            $display("🎉 ALL TESTS PASSED! (%0d/%0d)", test_count, test_count);
        end else begin
            $display("❌ SOME TESTS FAILED!");
        end
        
        #50;
        $finish;
    end

endmodule

testbench/Data_Memory_tb.vcd
$date
	Fri Dec  5 20:14:52 2025
$end
$version
	Icarus Verilog
$end
$timescale
	1ps
$end
$scope module Data_Memory_tb $end
$var wire 32 ! RD [31:0] $end
$var reg 32 " A [31:0] $end
$var reg 32 # WD [31:0] $end
$var reg 1 $ WE $end
$var reg 1 % clk $end
$var reg 32 & data_addr20 [31:0] $end
$var reg 32 ' data_addr30 [31:0] $end
$var reg 1 ( rst $end
$var reg 1 ) test_passed $end
$var integer 32 * test_count [31:0] $end
$scope module uut $end
$var wire 32 + A [31:0] $end
$var wire 32 , WD [31:0] $end
$var wire 1 $ WE $end
$var wire 1 % clk $end
$var wire 1 ( rst $end
$var wire 32 - RD [31:0] $end
$upscope $end
$upscope $end
$enddefinitions $end
$comment Show the parameter values. $end
$dumpall
$end
#0
$dumpvars
b0 -
b0 ,
b0 +
b0 *
1)
0(
bx '
bx &
0%
0$
b0 #
b0 "
b0 !
$end
#5000
1%
#10000
0%
#15000
1%
#20000
bx !
bx -
0%
1(
b1 *
#25000
1%
#30000
0%
#35000
1%
#40000
0%
b10010001101000101011001111000 #
b10010001101000101011001111000 ,
b10000 "
b10000 +
1$
#45000
b10010001101000101011001111000 !
b10010001101000101011001111000 -
1%
#50000
0%
#55000
1%
#60000
0%
0$
#65000
1%
#70000
0%
#75000
1%
#80000
bx !
bx -
0%
b11011110101011011011111011101111 #
b11011110101011011011111011101111 ,
b10100 "
b10100 +
b10 *
#85000
1%
#90000
0%
#95000
1%
#100000
0%
b10101011110011011110111100000000 #
b10101011110011011110111100000000 ,
b100000 "
b100000 +
1$
b11 *
#105000
b10101011110011011110111100000000 !
b10101011110011011110111100000000 -
1%
#110000
0%
#115000
1%
#120000
0%
0$
#125000
1%
#130000
bx !
bx -
0%
b11001010111111101011101010111110 #
b11001010111111101011101010111110 ,
b110000 "
b110000 +
1$
b10101011110011011110111100000000 &
#135000
b11001010111111101011101010111110 !
b11001010111111101011101010111110 -
1%
#140000
0%
#145000
1%
#150000
0%
0$
#155000
1%
#160000
b10101011110011011110111100000000 !
b10101011110011011110111100000000 -
0%
b100000 "
b100000 +
b11001010111111101011101010111110 '
#165000
1%
#170000
b10010001101000101011001111000 !
b10010001101000101011001111000 -
0%
b11111111111111111111111111111111 #
b11111111111111111111111111111111 ,
b10000 "
b10000 +
1$
b100 *
#175000
b11111111111111111111111111111111 !
b11111111111111111111111111111111 -
1%
#180000
0%
#185000
1%
#190000
0%
0$
#195000
1%
#200000
bx !
bx -
0%
b1 #
b1 ,
b0 "
b0 +
1$
b101 *
#205000
b1 !
b1 -
1%
#210000
0%
#215000
1%
#220000
0%
0$
#225000
1%
#230000
bx !
bx -
0%
b10000001000111010101111001101 #
b10000001000111010101111001101 ,
b1111111111 "
b1111111111 +
1$
#235000
b10000001000111010101111001101 !
b10000001000111010101111001101 -
1%
#240000
0%
#245000
1%
#250000
0%
0$
#255000
1%
#260000
bx !
bx -
0%
b10001000100010001000100010001 #
b10001000100010001000100010001 ,
1$
b100000000 "
b100000000 +
b110 *
#265000
b10001000100010001000100010001 !
b10001000100010001000100010001 -
1%
#270000
0%
#275000
1%
#280000
0%
0$
#285000
1%
#290000
bx !
bx -
0%
b100010001000100010001000100010 #
b100010001000100010001000100010 ,
1$
b100000100 "
b100000100 +
#295000
b100010001000100010001000100010 !
b100010001000100010001000100010 -
1%
#300000
0%
#305000
1%
#310000
0%
0$
#315000
1%
#320000
b0 !
b0 -
0%
0(
1$
b10111010110110111010110100000000 #
b10111010110110111010110100000000 ,
b1000000000 "
b1000000000 +
b111 *
#325000
1%
#330000
0%
#335000
1%
#340000
b10111010110110111010110100000000 !
b10111010110110111010110100000000 -
0%
0$
1(
#345000
1%
#350000
bx !
bx -
0%
b11001100110011001100110011001100 #
b11001100110011001100110011001100 ,
b1100000000 "
b1100000000 +
1$
b1000 *
#355000
b11001100110011001100110011001100 !
b11001100110011001100110011001100 -
1%
#356000
0$
#360000
0%
#361000
b1001 *
