define.v

// ALU_Ctrl
`define ALU_NONE                                4'b0000
`define ALU_SHIFTL                              4'b0001
`define ALU_SHIFTR                              4'b0010
`define ALU_SHIFTR_ARITH                        4'b0011
`define ALU_ADD                                 4'b0100
`define ALU_SUB                                 4'b0110
`define ALU_AND                                 4'b0111
`define ALU_OR                                  4'b1000
`define ALU_XOR                                 4'b1001
`define ALU_LESS_THAN                           4'b1010
`define ALU_LESS_THAN_SIGNED                    4'b1011


// sel_ext
`define Ext_ImmI      3'b000 // Immediate extension for I-type instructions
`define Ext_ImmS      3'b001
`define Ext_ImmB      3'b010
`define Ext_ImmU      3'b011
`define Ext_ImmJ      3'b100


//ALUOP
`define ALUOP_LOAD_STORE                        3'b000
`define ALUOP_RTYPE                             3'b001
`define ALUOP_ITYPE                            3'b010
`define ALUOP_BRANCH                            3'b011
`define ALUOP_J_UAL                          3'b100

//ResultSrc
`define FROM_ALU                                 3'b000          // from ALU Result
`define FROM_MEM                                 3'b001          // from Memory
`define FROM_PC_                                 3'b010          // PC + 4
`define FROM_IMM                                 3'b011          // ImmExt

// Opcode definitions
`define OPCODE_RTYPE  7'b011_0011  // R-type
`define OPCODE_ITYPE  7'b001_0011  // I-type 
`define OPCODE_LOAD   7'b000_0011  // lw
`define OPCODE_STORE  7'b010_0011  // sw
`define OPCODE_BRANCH 7'b110_0011  // B-Type(beq)
`define OPCODE_JAL    7'b110_1111  // J-Type(jal)
`define OPCODE_LUI    7'b011_0111  // U-Type(lui)

// sel_ext
`define ALU_IMM 1'b1 // the second ALU operand is immediate
`define ALU_REG 1'b0 // the second ALU operand is register


// PCSrc
`define PC_NOJUMP 1'b0 // PC + 4
`define PC_J_OFFSET 1'b1 // PC + immediate offset


//YES/NO
`define YES 1'b1
`define NO  1'b0

Instruction_Memory.v
module Instruction_Memory(rst,Address,ReadData);
    input rst;
    input [31:0] Address;
    output[31:0] ReadData;

    reg[31:0] mem[1023:0];
    assign ReadData = (rst == 1'b0)? 32'b0: mem[Address[31:2]];
    initial begin
        $readmemh("memfile.hex",mem);
    end

endmodule

testbench/Instruction_Memory_tb.v
`timescale 1ns / 1ps
`include "define.v"

module Instruction_Memory_tb;

    reg rst;
    reg [31:0] Address;
    wire [31:0] ReadData;
    
    reg test_passed;
    integer test_count;
    
    reg [31:0] data_0, data_1, data_2, data_3;
    reg [31:0] rapid_data_0, rapid_data_1, rapid_data_2;
    
    Instruction_Memory uut (
        .rst(rst),
        .Address(Address),
        .ReadData(ReadData)
    );
    
    function [31:0] simulate_next_pc;
        input [31:0] pc;
        input [31:0] instr;
        reg [6:0] opcode;
        reg [2:0] funct3;
        reg [4:0] rs1, rs2;
        reg [31:0] next_pc;
        reg signed [20:0] imm_j;
        reg signed [12:0] imm_b;
        reg branch_taken;
        begin
            opcode = instr[6:0];
            funct3 = instr[14:12];
            rs1 = instr[19:15];
            rs2 = instr[24:20];
            next_pc = pc + 4;  // Default: PC + 4
            branch_taken = 0;
            
            case (opcode)
                7'b1100011: begin // Branch instructions
                    imm_b = {instr[31], instr[7], instr[30:25], instr[11:8], 1'b0};
                    
                    // Check for infinite loop first (BEQ x0, x0, 0)
                    if (instr == 32'h00000063) begin
                        $display("PC: 0x%08x | Instruction: 0x%08x | INFINITE LOOP DETECTED (BEQ x0, x0, 0)", pc, instr);
                        simulate_next_pc = 32'hFFFFFFFF; // Signal end
                    end else begin
                        // Simulate branch condition (assuming simple test case)
                        // For BEQ (funct3 = 000): assume branch taken if rs1 == rs2 (we'll simulate this)
                        case (funct3)
                            3'b000: branch_taken = (rs1 == rs2) ? 1 : 0;  // BEQ - simplified assumption
                            3'b001: branch_taken = (rs1 != rs2) ? 1 : 0;  // BNE - simplified assumption
                            default: branch_taken = 0;
                        endcase
                        
                        if (branch_taken) begin
                            next_pc = pc + imm_b;
                            $display("PC: 0x%08x | Instruction: 0x%08x | Next PC: PC+IMM (0x%08x) [BRANCH TAKEN]", pc, instr, next_pc);
                            simulate_next_pc = next_pc;
                        end else begin
                            next_pc = pc + 4;
                            $display("PC: 0x%08x | Instruction: 0x%08x | Next PC: PC+4 (0x%08x) [BRANCH NOT TAKEN]", pc, instr, next_pc);
                            simulate_next_pc = next_pc;
                        end
                    end
                end
                
                7'b1101111: begin // JAL (unconditional jump)
                    imm_j = {instr[31], instr[19:12], instr[20], instr[30:21], 1'b0};
                    next_pc = pc + imm_j;
                    $display("PC: 0x%08x | Instruction: 0x%08x | Next PC: PC+IMM (0x%08x) [JUMP]", pc, instr, next_pc);
                    simulate_next_pc = next_pc;
                end
                
                default: begin
                    $display("PC: 0x%08x | Instruction: 0x%08x | Next PC: PC+4 (0x%08x)", pc, instr, next_pc);
                    simulate_next_pc = next_pc;
                end
            endcase
        end
    endfunction
    
    initial begin
        $dumpfile("Instruction_Memory_tb.vcd");
        $dumpvars(0, Instruction_Memory_tb);
    end
    
    initial begin
        test_passed = 1;
        test_count = 0;
        
        #10;
        
        // Test 8: Instruction execution simulation with proper PC progression
        rst = 1;
        
        // Simulate actual PC progression following branch logic
        Address = 32'h00000000;
        repeat (20) begin  // Maximum 20 instructions to prevent infinite loop
            #10;
            Address = simulate_next_pc(Address, ReadData);
            if (Address == 32'hFFFFFFFF) begin // End condition
                $display("Program execution completed or infinite loop detected");
                $finish;
            end
        end
        
        test_count = test_count + 1;
        
        #50;
        $finish;
    end

endmodule

testbench/Instruction_Memory_tb.vcd
$date
	Fri Dec  5 20:14:52 2025
$end
$version
	Icarus Verilog
$end
$timescale
	1ps
$end
$scope module Instruction_Memory_tb $end
$var wire 32 ! ReadData [31:0] $end
$var reg 32 " Address [31:0] $end
$var reg 1 # rst $end
$var reg 1 $ test_passed $end
$var integer 32 % test_count [31:0] $end
$scope function simulate_next_pc $end
$var reg 1 & branch_taken $end
$var reg 3 ' funct3 [2:0] $end
$var reg 13 ( imm_b [12:0] $end
$var reg 21 ) imm_j [20:0] $end
$var reg 32 * instr [31:0] $end
$var reg 32 + next_pc [31:0] $end
$var reg 7 , opcode [6:0] $end
$var reg 32 - pc [31:0] $end
$var reg 5 . rs1 [4:0] $end
$var reg 5 / rs2 [4:0] $end
$upscope $end
$scope module uut $end
$var wire 32 0 Address [31:0] $end
$var wire 1 # rst $end
$var wire 32 1 ReadData [31:0] $end
$upscope $end
$upscope $end
$enddefinitions $end
$comment Show the parameter values. $end
$dumpall
$end
#0
$dumpvars
bx 1
bx 0
bx /
bx .
bx -
bx ,
bx +
bx *
bx )
bx (
bx '
x&
b0 %
1$
x#
bx "
bx !
$end
#10000
b0 !
b0 1
b0 "
b0 0
1#
#20000
b101000000000000010010011 !
b101000000000000010010011 1
b100 "
b100 0
0&
b100 +
b0 /
b0 .
b0 '
b0 ,
b0 -
b0 *
#30000
b10100000000000100010011 !
b10100000000000100010011 1
b1000 "
b1000 0
b1000 +
b1010 /
b10011 ,
b100 -
b101000000000000010010011 *
#40000
b111100000000000110010011 !
b111100000000000110010011 1
b1100 "
b1100 0
b1100 +
b101 /
b1000 -
b10100000000000100010011 *
#50000
b1000001000001000110011 !
b1000001000001000110011 1
b10000 "
b10000 0
b10000 +
b1111 /
b1100 -
b111100000000000110010011 *
#60000
b1000000001000001000001010110011 !
b1000000001000001000001010110011 1
b10100 "
b10100 0
b10100 +
b10 /
b1 .
b110011 ,
b10000 -
b1000001000001000110011 *
#70000
b1000001111001100110011 !
b1000001111001100110011 1
b11000 "
b11000 0
b11000 +
b10100 -
b1000000001000001000001010110011 *
#80000
b1000001110001110110011 !
b1000001110001110110011 1
b11100 "
b11100 0
b11100 +
b111 '
b11000 -
b1000001111001100110011 *
#90000
b1000001100010000110011 !
b1000001100010000110011 1
b100000 "
b100000 0
b100000 +
b110 '
b11100 -
b1000001110001110110011 *
#100000
b11100011111010010010011 !
b11100011111010010010011 1
b100100 "
b100100 0
b100100 +
b100 '
b100000 -
b1000001100010000110011 *
#110000
b100000001110010100010011 !
b100000001110010100010011 1
b101000 "
b101000 0
b101000 +
b111 /
b11 .
b111 '
b10011 ,
b100100 -
b11100011111010010010011 *
#120000
b11100011100010110010011 !
b11100011100010110010011 1
b101100 "
b101100 0
b101100 +
b1000 /
b1 .
b110 '
b101000 -
b100000001110010100010011 *
#130000
b100001001011000010011 !
b100001001011000010011 1
b110000 "
b110000 0
b110000 +
b111 /
b11 .
b100 '
b101100 -
b11100011100010110010011 *
#140000
b100011101011010010011 !
b100011101011010010011 1
b110100 "
b110100 0
b110100 +
b1 /
b1 .
b1 '
b110000 -
b100001001011000010011 *
#150000
b1000000000100001101011100010011 !
b1000000000100001101011100010011 1
b111000 "
b111000 0
b111000 +
b11 .
b101 '
b110100 -
b100011101011010010011 *
#160000
b100010010011110110011 !
b100010010011110110011 1
b111100 "
b111100 0
b111100 +
b1 .
b111000 -
b1000000000100001101011100010011 *
#170000
b1000001011100000110011 !
b1000001011100000110011 1
b1000000 "
b1000000 0
b1000000 +
b10 .
b10 '
b110011 ,
b111100 -
b100010010011110110011 *
#180000
b111100001010100010010011 !
b111100001010100010010011 1
b1000100 "
b1000100 0
b1000100 +
b10 /
b1 .
b11 '
b1000000 -
b1000001011100000110011 *
#190000
b1100010011100100010011 !
b1100010011100100010011 1
b1001000 "
b1001000 0
b1001000 +
b1111 /
b10 '
b10011 ,
b1000100 -
b111100001010100010010011 *
#200000
b1100110110111 !
b1100110110111 1
b1001100 "
b1001100 0
b1001100 +
b11 /
b10 .
b11 '
b1001000 -
b1100010011100100010011 *
#210000
b110010000000010001000100011 !
b110010000000010001000100011 1
b1 %
b1010000 "
b1010000 0
b1010000 +
b0 /
b0 .
b1 '
b110111 ,
b1001100 -
b1100110110111 *
