define.v

// ALU_Ctrl
`define ALU_NONE                                4'b0000
`define ALU_SHIFTL                              4'b0001
`define ALU_SHIFTR                              4'b0010
`define ALU_SHIFTR_ARITH                        4'b0011
`define ALU_ADD                                 4'b0100
`define ALU_SUB                                 4'b0110
`define ALU_AND                                 4'b0111
`define ALU_OR                                  4'b1000
`define ALU_XOR                                 4'b1001
`define ALU_LESS_THAN                           4'b1010
`define ALU_LESS_THAN_SIGNED                    4'b1011


// sel_ext
`define Ext_ImmI      3'b000 // Immediate extension for I-type instructions
`define Ext_ImmS      3'b001
`define Ext_ImmB      3'b010
`define Ext_ImmU      3'b011
`define Ext_ImmJ      3'b100


//ALUOP
`define ALUOP_LOAD_STORE                        3'b000
`define ALUOP_RTYPE                             3'b001
`define ALUOP_ITYPE                            3'b010
`define ALUOP_BRANCH                            3'b011
`define ALUOP_J_UAL                          3'b100

//ResultSrc
`define FROM_ALU                                 3'b000          // from ALU Result
`define FROM_MEM                                 3'b001          // from Memory
`define FROM_PC_                                 3'b010          // PC + 4
`define FROM_IMM                                 3'b011          // ImmExt

// Opcode definitions
`define OPCODE_RTYPE  7'b011_0011  // R-type
`define OPCODE_ITYPE  7'b001_0011  // I-type 
`define OPCODE_LOAD   7'b000_0011  // lw
`define OPCODE_STORE  7'b010_0011  // sw
`define OPCODE_BRANCH 7'b110_0011  // B-Type(beq)
`define OPCODE_JAL    7'b110_1111  // J-Type(jal)
`define OPCODE_LUI    7'b011_0111  // U-Type(lui)

// sel_ext
`define ALU_IMM 1'b1 // the second ALU operand is immediate
`define ALU_REG 1'b0 // the second ALU operand is register


// PCSrc
`define PC_NOJUMP 1'b0 // PC + 4
`define PC_J_OFFSET 1'b1 // PC + immediate offset


//YES/NO
`define YES 1'b1
`define NO  1'b0

Instruction_Memory.v
module Instruction_Memory(rst,Address,ReadData);
    input rst;
    input [31:0] Address;
    output[31:0] ReadData;

    reg[31:0] mem[1023:0];
    assign ReadData = (rst == 1'b0)? 32'b0: mem[Address[31:2]];
    initial begin
        $readmemh("memfile.hex",mem);
    end

endmodule

testbench/Instruction_Memory_tb.v
`timescale 1ns / 1ps
`include "define.v"

module Instruction_Memory_tb;

    // Testbench signals
    reg rst;
    reg [31:0] Address;
    wire [31:0] ReadData;
    
    // Test tracking
    reg test_passed;
    integer test_count;
    
    // Temp variables for tests
    reg [31:0] data_0, data_1, data_2, data_3;
    reg [31:0] rapid_data_0, rapid_data_1, rapid_data_2;
    
    // Use existing memfile.hex for testing
    
    // Instantiate the Instruction Memory (modified to use test file)
    // Note: We need to modify the module to use a parameter for filename
    // For this testbench, we'll test with the existing memfile.hex
    Instruction_Memory uut (
        .rst(rst),
        .Address(Address),
        .ReadData(ReadData)
    );
    
    // VCD dump
    initial begin
        $dumpfile("Instruction_Memory_tb.vcd");
        $dumpvars(0, Instruction_Memory_tb);
    end
    
    // Test sequence
    initial begin
        $display("=== Instruction Memory Module Testbench ===");
        $display("Time\tRst\tAddress\t\tReadData\tTest Description");
        
        test_passed = 1;
        test_count = 0;
        
        // Wait for memory file to be processed
        #10;
        
        // Test 1: Reset functionality
        $display("\n--- Test 1: Reset Functionality ---");
        rst = 0;
        Address = 32'h00000000;
        #10;
        $display("%0t\t%b\t%08x\t%08x\tReset=0", $time, rst, Address, ReadData);
        
        if (ReadData == 32'h0) begin
            $display("✓ PASS: Reset properly disables memory output");
        end else begin
            $display("✗ FAIL: Reset should disable output, got %08x", ReadData);
            test_passed = 0;
        end
        test_count = test_count + 1;
        
        // Test 2: Normal memory read (rst=1)
        $display("\n--- Test 2: Normal Memory Access ---");
        rst = 1;
        Address = 32'h00000000; // Word address 0
        #10;
        $display("%0t\t%b\t%08x\t%08x\tAddr=0", $time, rst, Address, ReadData);
        
        // We expect to read the first instruction from memfile.hex
        if (ReadData != 32'h0) begin
            $display("✓ PASS: Memory read enabled when rst=1, data=%08x", ReadData);
        end else begin
            $display("⚠ INFO: Memory location 0 contains 0 (might be correct)");
        end
        test_count = test_count + 1;
        
        // Test 3: Word-aligned address access
        $display("\n--- Test 3: Word-Aligned Address Access ---");
        
        // Test address 0x00000004 (should access mem[1])
        Address = 32'h00000004;
        #10;
        $display("%0t\t%b\t%08x\t%08x\tAddr=4", $time, rst, Address, ReadData);
        
        // Test address 0x00000008 (should access mem[2])
        Address = 32'h00000008;
        #10;
        $display("%0t\t%b\t%08x\t%08x\tAddr=8", $time, rst, Address, ReadData);
        
        // Test address 0x0000000C (should access mem[3])
        Address = 32'h0000000C;
        #10;
        $display("%0t\t%b\t%08x\t%08x\tAddr=12", $time, rst, Address, ReadData);
        
        $display("✓ INFO: Word-aligned addresses tested (mem uses Address[31:2])");
        test_count = test_count + 1;
        
        // Test 4: Non-word-aligned addresses (should still work due to [31:2])
        $display("\n--- Test 4: Non-Word-Aligned Address Behavior ---");
        
        Address = 32'h00000001; // Should still access mem[0]
        #10;
        data_1 = ReadData;
        $display("%0t\t%b\t%08x\t%08x\tAddr=1", $time, rst, Address, ReadData);
        
        Address = 32'h00000002; // Should still access mem[0] 
        #10;
        data_2 = ReadData;
        $display("%0t\t%b\t%08x\t%08x\tAddr=2", $time, rst, Address, ReadData);
        
        Address = 32'h00000003; // Should still access mem[0]
        #10;
        data_3 = ReadData;
        $display("%0t\t%b\t%08x\t%08x\tAddr=3", $time, rst, Address, ReadData);
        
        Address = 32'h00000000; // Reference: mem[0]
        #10;
        data_0 = ReadData;
        
        if (data_0 == data_1 && data_0 == data_2 && data_0 == data_3) begin
            $display("✓ PASS: Non-word-aligned addresses correctly map to same word");
        end else begin
            $display("✗ FAIL: Address alignment not working properly");
            test_passed = 0;
        end
        test_count = test_count + 1;
        
        // Test 5: Reset during operation
        $display("\n--- Test 5: Reset During Operation ---");
        Address = 32'h00000008;
        rst = 1;
        #5;
        rst = 0; // Reset while address is set
        #10;
        $display("%0t\t%b\t%08x\t%08x\tReset During Op", $time, rst, Address, ReadData);
        
        if (ReadData == 32'h0) begin
            $display("✓ PASS: Reset immediately disables output");
        end else begin
            $display("✗ FAIL: Reset should immediately disable output");
            test_passed = 0;
        end
        test_count = test_count + 1;
        
        // Test 6: Large address values
        $display("\n--- Test 6: Large Address Values ---");
        rst = 1;
        
        // Test boundary addresses
        Address = 32'h00000FFC; // Should access mem[1023] (last valid address)
        #10;
        $display("%0t\t%b\t%08x\t%08x\tMax Valid Addr", $time, rst, Address, ReadData);
        
        // Test very large address (beyond memory bounds)
        Address = 32'h00001000; // Should access mem[1024] - undefined behavior
        #10;
        $display("%0t\t%b\t%08x\t%08x\tBeyond Bounds", $time, rst, Address, ReadData);
        
        $display("✓ INFO: Large address behavior tested (implementation dependent)");
        test_count = test_count + 1;
        
        // Test 7: Rapid address changes
        $display("\n--- Test 7: Rapid Address Changes ---");
        
        Address = 32'h00000000; #2;
        rapid_data_0 = ReadData;
        
        Address = 32'h00000004; #2;  
        rapid_data_1 = ReadData;
        
        Address = 32'h00000008; #2;
        rapid_data_2 = ReadData;
        
        $display("%0t\t%b\t%08x\t%08x\tRapid Access", $time, rst, Address, ReadData);
        
        // Check that memory responds immediately to address changes
        Address = 32'h00000000; #1;
        if (ReadData == rapid_data_0) begin
            $display("✓ PASS: Memory responds immediately to address changes");
        end else begin
            $display("✗ FAIL: Memory should respond immediately to address changes");
            test_passed = 0;
        end
        test_count = test_count + 1;
        
        // Test 8: Check actual memory content from memfile.hex
        $display("\n--- Test 8: Verify Memory File Loading ---");
        
        // Read the first few locations and display their contents
        Address = 32'h00000000; #10;
        $display("mem[0] (addr 0x00000000): 0x%08x", ReadData);
        
        Address = 32'h00000004; #10;  
        $display("mem[1] (addr 0x00000004): 0x%08x", ReadData);
        
        $display("✓ INFO: Memory file content verified");
        test_count = test_count + 1;
        
        // Final results
        $display("\n=== Instruction_Memory Testbench Complete ===");
        if (test_passed) begin
            $display("🎉 ALL TESTS PASSED! (%0d/%0d)", test_count, test_count);
        end else begin
            $display("❌ SOME TESTS FAILED!");
        end
        
        #50;
        $finish;
    end

endmodule

testbench/Instruction_Memory_tb.vcd
$date
	Thu Dec  4 17:04:10 2025
$end
$version
	Icarus Verilog
$end
$timescale
	1ps
$end
$scope module Instruction_Memory_tb $end
$var wire 32 ! ReadData [31:0] $end
$var reg 32 " Address [31:0] $end
$var reg 32 # data_0 [31:0] $end
$var reg 32 $ data_1 [31:0] $end
$var reg 32 % data_2 [31:0] $end
$var reg 32 & data_3 [31:0] $end
$var reg 32 ' rapid_data_0 [31:0] $end
$var reg 32 ( rapid_data_1 [31:0] $end
$var reg 32 ) rapid_data_2 [31:0] $end
$var reg 1 * rst $end
$var reg 1 + test_passed $end
$var integer 32 , test_count [31:0] $end
$scope module uut $end
$var wire 32 - Address [31:0] $end
$var wire 1 * rst $end
$var wire 32 . ReadData [31:0] $end
$upscope $end
$upscope $end
$enddefinitions $end
$comment Show the parameter values. $end
$dumpall
$end
#0
$dumpvars
bx .
bx -
b0 ,
1+
x*
bx )
bx (
bx '
bx &
bx %
bx $
bx #
bx "
bx !
$end
#10000
b0 !
b0 .
b0 "
b0 -
0*
#20000
b11000101110001110110011 !
b11000101110001110110011 .
1*
b1 ,
#30000
b11000101111010000110011 !
b11000101111010000110011 .
b100 "
b100 -
b10 ,
#40000
bx !
bx .
b1000 "
b1000 -
#50000
b1100 "
b1100 -
#60000
b11000101110001110110011 !
b11000101110001110110011 .
b1 "
b1 -
b11 ,
#70000
b10 "
b10 -
b11000101110001110110011 $
#80000
b11 "
b11 -
b11000101110001110110011 %
#90000
b0 "
b0 -
b11000101110001110110011 &
#100000
bx !
bx .
b1000 "
b1000 -
b100 ,
b11000101110001110110011 #
#105000
b0 !
b0 .
0*
#115000
bx !
bx .
b111111111100 "
b111111111100 -
1*
b101 ,
#125000
b1000000000000 "
b1000000000000 -
#135000
b11000101110001110110011 !
b11000101110001110110011 .
b0 "
b0 -
b110 ,
#137000
b11000101111010000110011 !
b11000101111010000110011 .
b100 "
b100 -
b11000101110001110110011 '
#139000
bx !
bx .
b1000 "
b1000 -
b11000101111010000110011 (
#141000
b11000101110001110110011 !
b11000101110001110110011 .
b0 "
b0 -
#142000
b111 ,
#152000
b11000101111010000110011 !
b11000101111010000110011 .
b100 "
b100 -
#162000
b1000 ,
