define.v

// ALU_Ctrl
`define ALU_NONE                                4'b0000
`define ALU_SHIFTL                              4'b0001
`define ALU_SHIFTR                              4'b0010
`define ALU_SHIFTR_ARITH                        4'b0011
`define ALU_ADD                                 4'b0100
`define ALU_SUB                                 4'b0110
`define ALU_AND                                 4'b0111
`define ALU_OR                                  4'b1000
`define ALU_XOR                                 4'b1001
`define ALU_LESS_THAN                           4'b1010
`define ALU_LESS_THAN_SIGNED                    4'b1011


// sel_ext
`define Ext_ImmI      3'b000 // Immediate extension for I-type instructions
`define Ext_ImmS      3'b001
`define Ext_ImmB      3'b010
`define Ext_ImmU      3'b011
`define Ext_ImmJ      3'b100


//ALUOP
`define ALUOP_LOAD_STORE                        3'b000
`define ALUOP_RTYPE                             3'b001
`define ALUOP_ITYPE                            3'b010
`define ALUOP_BRANCH                            3'b011
`define ALUOP_J_UAL                          3'b100

//ResultSrc
`define FROM_ALU                                 3'b000          // from ALU Result
`define FROM_MEM                                 3'b001          // from Memory
`define FROM_PC_                                 3'b010          // PC + 4
`define FROM_IMM                                 3'b011          // ImmExt

// Opcode definitions
`define OPCODE_RTYPE  7'b011_0011  // R-type
`define OPCODE_ITYPE  7'b001_0011  // I-type 
`define OPCODE_LOAD   7'b000_0011  // lw
`define OPCODE_STORE  7'b010_0011  // sw
`define OPCODE_BRANCH 7'b110_0011  // B-Type(beq)
`define OPCODE_JAL    7'b110_1111  // J-Type(jal)
`define OPCODE_LUI    7'b011_0111  // U-Type(lui)

// sel_ext
`define ALU_IMM 1'b1 // the second ALU operand is immediate
`define ALU_REG 1'b0 // the second ALU operand is register


// PCSrc
`define PC_NOJUMP 1'b0 // PC + 4
`define PC_J_OFFSET 1'b1 // PC + immediate offset


//YES/NO
`define YES 1'b1
`define NO  1'b0

NPC.v
`include "define.v"
module NPC( PC, PCSrc, IMMEXT, NPC );  // next pc module
   input  [31:0] PC;        
   input  PCSrc;    
   input  [31:0] IMMEXT;       
   output reg [31:0] NPC;   
   
   wire [31:0] PCPLUS4;
   assign PCPLUS4 = PC + 4; 
   
   always @(*) begin
      case (PCSrc)
          `PC_NOJUMP:  NPC = PCPLUS4;   // NPC computes addr
          `PC_J_OFFSET: NPC = PC+IMMEXT;    //B type, NPC computes addr
          default:     NPC = PCPLUS4;
      endcase
   end
   
endmodule

testbench/NPC_tb.v
`timescale 1ns/1ps

module NPC_tb();
    // Include define file for PCSrc constants
    `include "../src/define.v"
    
    // Testbench signals
    reg [31:0] PC;
    reg PCSrc;  // Changed to 1-bit
    reg [31:0] IMMEXT;
    wire [31:0] NPC;
    
    // Instantiate the NPC module
    NPC uut (
        .PC(PC),
        .PCSrc(PCSrc),
        .IMMEXT(IMMEXT),
        .NPC(NPC)
    );
    
    // Test sequence
    initial begin
        // Initialize signals
        PC = 32'h00000000;
        PCSrc = 1'b0;
        IMMEXT = 32'h00000000;
        
        // Create VCD file for waveform viewing
        $dumpfile("NPC_tb.vcd");
        $dumpvars(0, NPC_tb);
        
        $display("=== NPC Module Testbench ===");
        $display("Time\tPC\t\tPCSrc\tIMMEXT\t\tNPC\t\tExpected");
        
        #1; // Small delay for signal propagation
        
        // Test 1: Sequential execution (PC + 4)
        $display("\n--- Test 1: Sequential execution (PC + 4) ---");
        PC = 32'h00000000;
        PCSrc = `PC_NOJUMP;  // 1'b0 - PC + 4
        IMMEXT = 32'h12345678; // Should be ignored
        #10;
        $display("%0t\t%h\t%b\t%h\t%h\t%h", $time, PC, PCSrc, IMMEXT, NPC, PC + 4);
        if (NPC == PC + 4) 
            $display("✓ PASS: NPC = PC + 4 = 0x00000004");
        else 
            $display("✗ FAIL: Expected 0x00000004, got %h", NPC);
        
        // Test 2: Different PC values with PC + 4
        $display("\n--- Test 2: Different PC values with PC + 4 ---");
        PC = 32'h00001000;
        PCSrc = `PC_NOJUMP;  // 1'b0 - PC + 4
        IMMEXT = 32'hFFFFFFFF; // Should be ignored
        #10;
        $display("%0t\t%h\t%b\t%h\t%h\t%h", $time, PC, PCSrc, IMMEXT, NPC, PC + 4);
        if (NPC == 32'h00001004) 
            $display("✓ PASS: NPC = PC + 4 = 0x00001004");
        else 
            $display("✗ FAIL: Expected 0x00001004, got %h", NPC);
        
        // Test 3: Branch/Jump with positive offset
        $display("\n--- Test 3: Branch/Jump with positive offset ---");
        PC = 32'h00002000;
        PCSrc = `PC_J_OFFSET;  // 1'b1 - PC + IMMEXT
        IMMEXT = 32'h00000010; // +16 offset
        #10;
        $display("%0t\t%h\t%b\t%h\t%h\t%h", $time, PC, PCSrc, IMMEXT, NPC, PC + IMMEXT);
        if (NPC == 32'h00002010) 
            $display("✓ PASS: NPC = PC + IMMEXT = 0x00002010");
        else 
            $display("✗ FAIL: Expected 0x00002010, got %h", NPC);
        
        // Test 4: Branch/Jump with negative offset (signed)
        $display("\n--- Test 4: Branch/Jump with negative offset ---");
        PC = 32'h00003000;
        PCSrc = `PC_J_OFFSET;  // 1'b1 - PC + IMMEXT
        IMMEXT = 32'hFFFFFFF0; // -16 offset (2's complement)
        #10;
        $display("%0t\t%h\t%b\t%h\t%h\t%h", $time, PC, PCSrc, IMMEXT, NPC, PC + IMMEXT);
        if (NPC == 32'h00002FF0) 
            $display("✓ PASS: NPC = PC + IMMEXT = 0x00002FF0 (negative offset)");
        else 
            $display("✗ FAIL: Expected 0x00002FF0, got %h", NPC);
        
        // Test 5: Large positive offset
        $display("\n--- Test 5: Large positive offset ---");
        PC = 32'h00000100;
        PCSrc = `PC_J_OFFSET;  // 1'b1 - PC + IMMEXT
        IMMEXT = 32'h00001000; // +4096 offset
        #10;
        $display("%0t\t%h\t%b\t%h\t%h\t%h", $time, PC, PCSrc, IMMEXT, NPC, PC + IMMEXT);
        if (NPC == 32'h00001100) 
            $display("✓ PASS: NPC = PC + IMMEXT = 0x00001100 (large offset)");
        else 
            $display("✗ FAIL: Expected 0x00001100, got %h", NPC);
        
        // Test 6: Zero offset
        $display("\n--- Test 6: Zero offset ---");
        PC = 32'h00005000;
        PCSrc = `PC_J_OFFSET;  // 1'b1 - PC + IMMEXT
        IMMEXT = 32'h00000000; // Zero offset
        #10;
        $display("%0t\t%h\t%b\t%h\t%h\t%h", $time, PC, PCSrc, IMMEXT, NPC, PC);
        if (NPC == PC) 
            $display("✓ PASS: NPC = PC = 0x00005000 (zero offset)");
        else 
            $display("✗ FAIL: Expected 0x00005000, got %h", NPC);
        
        // Test 7: Edge case - Maximum addresses
        $display("\n--- Test 7: Edge case - Maximum addresses ---");
        PC = 32'hFFFFFFFC;
        PCSrc = `PC_NOJUMP;  // 1'b0 - PC + 4
        IMMEXT = 32'h00000000;
        #10;
        $display("%0t\t%h\t%b\t%h\t%h\t%h", $time, PC, PCSrc, IMMEXT, NPC, PC + 4);
        if (NPC == 32'h00000000) // Overflow wraps around
            $display("✓ PASS: PC + 4 overflow handled correctly: 0x00000000");
        else 
            $display("ⓘ INFO: PC + 4 = %h (may overflow depending on implementation)", NPC);
        
        // Test 8: Rapid PCSrc switching
        $display("\n--- Test 8: Rapid PCSrc switching ---");
        PC = 32'h00007000;
        IMMEXT = 32'h00000100;
        
        PCSrc = `PC_NOJUMP;  // 1'b0 - PC + 4
        #1;
        if (NPC == 32'h00007004) 
            $display("✓ PASS: Quick switch to PC+4 works");
        
        PCSrc = `PC_J_OFFSET;  // 1'b1 - PC + IMMEXT
        #1;
        if (NPC == 32'h00007100) 
            $display("✓ PASS: Quick switch to PC+IMMEXT works");
        
        PCSrc = `PC_NOJUMP;  // 1'b0 - PC + 4
        #1;
        if (NPC == 32'h00007004) 
            $display("✓ PASS: Quick switch back to PC+4 works");
        
        $display("\n=== NPC Testbench Complete ===");
        #50;
        $finish;
    end
    
    // Monitor for debugging
    always @(*) begin
        #0.1; // Small delay to avoid race conditions
        if (PC !== 32'hxxxxxxxx && PCSrc !== 1'bx && IMMEXT !== 32'hxxxxxxxx) begin
            case (PCSrc)
                `PC_NOJUMP: begin  // 1'b0 - PC + 4
                    if (NPC !== PC + 4)
                        $display("WARNING: NPC mismatch at time %0t. Expected %h, got %h", 
                                $time, PC + 4, NPC);
                end
                `PC_J_OFFSET: begin  // 1'b1 - PC + IMMEXT
                    if (NPC !== PC + IMMEXT)
                        $display("WARNING: NPC mismatch at time %0t. Expected %h, got %h", 
                                $time, PC + IMMEXT, NPC);
                end
                default: begin
                    if (NPC !== PC + 4)
                        $display("WARNING: Default case mismatch at time %0t. Expected %h, got %h", 
                                $time, PC + 4, NPC);
                end
            endcase
        end
    end
    
endmodule

testbench/NPC_tb.vcd
$date
	Fri Dec  5 20:14:52 2025
$end
$version
	Icarus Verilog
$end
$timescale
	1ps
$end
$scope module NPC_tb $end
$var wire 32 ! NPC [31:0] $end
$var reg 32 " IMMEXT [31:0] $end
$var reg 32 # PC [31:0] $end
$var reg 1 $ PCSrc $end
$scope module uut $end
$var wire 32 % IMMEXT [31:0] $end
$var wire 32 & PC [31:0] $end
$var wire 1 $ PCSrc $end
$var wire 32 ' PCPLUS4 [31:0] $end
$var reg 32 ( NPC [31:0] $end
$upscope $end
$upscope $end
$enddefinitions $end
$comment Show the parameter values. $end
$dumpall
$end
#0
$dumpvars
b100 (
b100 '
b0 &
b0 %
0$
b0 #
b0 "
b100 !
$end
#1000
b10010001101000101011001111000 "
b10010001101000101011001111000 %
#11000
b1000000000100 !
b1000000000100 (
b11111111111111111111111111111111 "
b11111111111111111111111111111111 %
b1000000000100 '
b1000000000000 #
b1000000000000 &
#21000
b10000000010000 !
b10000000010000 (
b10000 "
b10000 %
1$
b10000000000100 '
b10000000000000 #
b10000000000000 &
#31000
b10111111110000 !
b10111111110000 (
b11111111111111111111111111110000 "
b11111111111111111111111111110000 %
b11000000000100 '
b11000000000000 #
b11000000000000 &
#41000
b1000100000000 !
b1000100000000 (
b1000000000000 "
b1000000000000 %
b100000100 '
b100000000 #
b100000000 &
#51000
b101000000000000 !
b101000000000000 (
b0 "
b0 %
b101000000000100 '
b101000000000000 #
b101000000000000 &
#61000
b0 !
b0 (
0$
b0 '
b11111111111111111111111111111100 #
b11111111111111111111111111111100 &
#71000
b111000000000100 !
b111000000000100 (
b100000000 "
b100000000 %
b111000000000100 '
b111000000000000 #
b111000000000000 &
#72000
b111000100000000 !
b111000100000000 (
1$
#73000
b111000000000100 !
b111000000000100 (
0$
