PC.v
module PC(clk,rst,PC,NPC);
    input clk;
    input rst;
    input [31:0] NPC; // Next Instruction Address
    output reg [31:0] PC; // current Instrcution Address

    always @(posedge clk or negedge rst) begin
        if (~rst) begin
            PC <= 32'h0000_0000;
        end
        else begin
            PC <= NPC;
           //$write("PC: %h\n", NPC);
        end
    end
endmodule

testbench/PC_tb.v
`timescale 1ns/1ps

module PC_tb();
    // Testbench signals
    reg clk;
    reg rst;
    reg [31:0] NPC;
    wire [31:0] PC;
    
    // Instantiate the PC module
    PC uut (
        .clk(clk),
        .rst(rst),
        .PC(PC),
        .NPC(NPC)
    );
    
    // Clock generation
    initial begin
        clk = 0;
        forever #5 clk = ~clk; // 100MHz clock (10ns period)
    end
    
    // Test sequence
    initial begin
        // Initialize signals
        rst = 0;
        NPC = 32'h00000000;
        
        // Create VCD file for waveform viewing
        $dumpfile("PC_tb.vcd");
        $dumpvars(0, PC_tb);
        
        $display("=== PC Module Testbench ===");
        $display("Time\tRST\tNPC\t\tPC");
        $monitor("%0t\t%b\t%h\t%h", $time, rst, NPC, PC);
        
        // Test 1: Reset functionality (active low reset)
        #10;
        $display("\n--- Test 1: Reset functionality ---");
        rst = 0; // Reset is active low
        #20;
        if (PC == 32'h00000000) 
            $display("✓ PASS: Reset sets PC to 0x00000000");
        else 
            $display("✗ FAIL: Reset should set PC to 0x00000000, got %h", PC);
        
        // Test 2: Normal PC update
        $display("\n--- Test 2: Normal PC update ---");
        rst = 1; // Release reset
        NPC = 32'h00000004;
        #10;
        if (PC == 32'h00000004) 
            $display("✓ PASS: PC correctly updates to 0x00000004");
        else 
            $display("✗ FAIL: PC should be 0x00000004, got %h", PC);
        
        // Test 3: Sequential PC updates
        $display("\n--- Test 3: Sequential PC updates ---");
        NPC = 32'h00000008;
        #10;
        if (PC == 32'h00000008) 
            $display("✓ PASS: PC correctly updates to 0x00000008");
        else 
            $display("✗ FAIL: PC should be 0x00000008, got %h", PC);
            
        NPC = 32'h0000000C;
        #10;
        if (PC == 32'h0000000C) 
            $display("✓ PASS: PC correctly updates to 0x0000000C");
        else 
            $display("✗ FAIL: PC should be 0x0000000C, got %h", PC);
        
        // Test 4: Large address values
        $display("\n--- Test 4: Large address values ---");
        NPC = 32'hFFFFFFFC;
        #10;
        if (PC == 32'hFFFFFFFC) 
            $display("✓ PASS: PC correctly handles large address 0xFFFFFFFC");
        else 
            $display("✗ FAIL: PC should be 0xFFFFFFFC, got %h", PC);
        
        // Test 5: Reset during operation
        $display("\n--- Test 5: Reset during operation ---");
        NPC = 32'h12345678;
        #5; // Half clock cycle
        rst = 0; // Assert reset
        #10;
        if (PC == 32'h00000000) 
            $display("✓ PASS: Reset works correctly during operation");
        else 
            $display("✗ FAIL: Reset should set PC to 0x00000000, got %h", PC);
            
        rst = 1; // Release reset
        #10;
        
        // Test 6: Zero address
        $display("\n--- Test 6: Zero address ---");
        NPC = 32'h00000000;
        #10;
        if (PC == 32'h00000000) 
            $display("✓ PASS: PC correctly handles zero address");
        else 
            $display("✗ FAIL: PC should be 0x00000000, got %h", PC);
        
        $display("\n=== PC Testbench Complete ===");
        #50;
        $finish;
    end
    
    // Error checking for undefined states
    always @(PC) begin
        if (PC === 32'hxxxxxxxx) begin
            $display("ERROR: PC is in undefined state at time %0t", $time);
        end
    end
    
endmodule

testbench/PC_tb.vcd
$date
	Fri Dec  5 20:14:52 2025
$end
$version
	Icarus Verilog
$end
$timescale
	1ps
$end
$scope module PC_tb $end
$var wire 32 ! PC [31:0] $end
$var reg 32 " NPC [31:0] $end
$var reg 1 # clk $end
$var reg 1 $ rst $end
$scope module uut $end
$var wire 32 % NPC [31:0] $end
$var wire 1 # clk $end
$var wire 1 $ rst $end
$var reg 32 & PC [31:0] $end
$upscope $end
$upscope $end
$enddefinitions $end
$comment Show the parameter values. $end
$dumpall
$end
#0
$dumpvars
bx &
b0 %
0$
0#
b0 "
bx !
$end
#5000
b0 !
b0 &
1#
#10000
0#
#15000
1#
#20000
0#
#25000
1#
#30000
0#
b100 "
b100 %
1$
#35000
b100 !
b100 &
1#
#40000
0#
b1000 "
b1000 %
#45000
b1000 !
b1000 &
1#
#50000
0#
b1100 "
b1100 %
#55000
b1100 !
b1100 &
1#
#60000
0#
b11111111111111111111111111111100 "
b11111111111111111111111111111100 %
#65000
b11111111111111111111111111111100 !
b11111111111111111111111111111100 &
1#
#70000
0#
b10010001101000101011001111000 "
b10010001101000101011001111000 %
#75000
b0 !
b0 &
1#
0$
#80000
0#
#85000
b10010001101000101011001111000 !
b10010001101000101011001111000 &
1#
1$
#90000
0#
#95000
b0 !
b0 &
1#
b0 "
b0 %
