define.v

// ALU_Ctrl
`define ALU_NONE                                4'b0000
`define ALU_SHIFTL                              4'b0001
`define ALU_SHIFTR                              4'b0010
`define ALU_SHIFTR_ARITH                        4'b0011
`define ALU_ADD                                 4'b0100
`define ALU_SUB                                 4'b0110
`define ALU_AND                                 4'b0111
`define ALU_OR                                  4'b1000
`define ALU_XOR                                 4'b1001
`define ALU_LESS_THAN                           4'b1010
`define ALU_LESS_THAN_SIGNED                    4'b1011


// sel_ext
`define Ext_ImmI      3'b000 // Immediate extension for I-type instructions
`define Ext_ImmS      3'b001
`define Ext_ImmB      3'b010
`define Ext_ImmU      3'b011
`define Ext_ImmJ      3'b100


//ALUOP
`define ALUOP_LOAD_STORE                        3'b000
`define ALUOP_RTYPE                             3'b001
`define ALUOP_ITYPE                            3'b010
`define ALUOP_BRANCH                            3'b011
`define ALUOP_J_UAL                          3'b100

//ResultSrc
`define FROM_ALU                                 3'b000          // from ALU Result
`define FROM_MEM                                 3'b001          // from Memory
`define FROM_PC_                                 3'b010          // PC + 4
`define FROM_IMM                                 3'b011          // ImmExt

// Opcode definitions
`define OPCODE_RTYPE  7'b011_0011  // R-type
`define OPCODE_ITYPE  7'b001_0011  // I-type 
`define OPCODE_LOAD   7'b000_0011  // lw
`define OPCODE_STORE  7'b010_0011  // sw
`define OPCODE_BRANCH 7'b110_0011  // B-Type(beq)
`define OPCODE_JAL    7'b110_1111  // J-Type(jal)
`define OPCODE_LUI    7'b011_0111  // U-Type(lui)

// sel_ext
`define ALU_IMM 1'b1 // the second ALU operand is immediate
`define ALU_REG 1'b0 // the second ALU operand is register


// PCSrc
`define PC_NOJUMP 1'b0 // PC + 4
`define PC_J_OFFSET 1'b1 // PC + immediate offset


//YES/NO
`define YES 1'b1
`define NO  1'b0

Register_File.v
module Register_File(clk,rst,WriteEnable3,WD3,Address1,Address2,Address3,RD1,RD2);
    input clk,rst,WriteEnable3;
    input [4:0]Address1,Address2,Address3;
    input [31:0]WD3;
    output[31:0] RD1,RD2;
    
    reg[31:0] Register [31:0]; // we have 32 registers, each is 32 bits wide
    integer i;
    always @(posedge clk or posedge rst) begin
        if(rst) begin
            for(i = 0; i < 32; i = i + 1) begin
                Register[i] <= 32'd0;
            end
        end else if(WriteEnable3 && Address3 != 5'd0) begin
            Register[Address3] <= WD3; 
        end
    end
    assign RD1 = Register[Address1];
    assign RD2 = Register[Address2];

    // initial begin
    //     Register[5] = 32'h00000005;
    //     Register[6] = 32'h00000004;
    // end

endmodule

testbench/Register_File_tb.v
`timescale 1ns / 1ps
`include "define.v"

module Register_File_tb;

    // Testbench signals
    reg clk;
    reg rst;
    reg WriteEnable3;
    reg [4:0] Address1, Address2, Address3;
    reg [31:0] WD3;
    wire [31:0] RD1, RD2;
    
    // Test tracking
    reg test_passed;
    integer test_count;
    
    // Instantiate the Register File
    Register_File uut (
        .clk(clk),
        .rst(rst),
        .WriteEnable3(WriteEnable3),
        .WD3(WD3),
        .Address1(Address1),
        .Address2(Address2),
        .Address3(Address3),
        .RD1(RD1),
        .RD2(RD2)
    );
    
    // Generate clock
    always begin
        clk = 0; #5;
        clk = 1; #5;
    end
    
    // VCD dump
    initial begin
        $dumpfile("Register_File_tb.vcd");
        $dumpvars(0, Register_File_tb);
    end
    
    // Test sequence
    initial begin
        $display("=== Register File Module Testbench ===");
        $display("Time\tRst\tWE3\tAddr1\tAddr2\tAddr3\tWD3\t\tRD1\t\tRD2\t\tTest");
        
        test_passed = 1;
        test_count = 0;
        
        // Initialize signals
        rst = 0;  // Start with active-low reset active
        WriteEnable3 = 0;
        Address1 = 0;
        Address2 = 0;
        Address3 = 0;
        WD3 = 0;
        
        // Test 1: Reset functionality
        $display("\n--- Test 1: Reset Functionality ---");
        rst = 0; // Apply active-low reset
        #20;
        $display("%0t\t%b\t%b\t%2d\t%2d\t%2d\t%08x\t%08x\t%08x\tReset", 
                 $time, rst, WriteEnable3, Address1, Address2, Address3, WD3, RD1, RD2);
        
        if (RD1 == 32'h0 && RD2 == 32'h0) begin
            $display("✓ PASS: Reset clears registers");
        end else begin
            $display("✗ FAIL: Reset should clear all registers to 0");
            test_passed = 0;
        end
        test_count = test_count + 1;
        
        rst = 1; // Release reset for normal operation
        #10;
        
        // Test 2: Write to register 0 should be ignored
        $display("\n--- Test 2: Register 0 Write Protection ---");
        WriteEnable3 = 1;
        Address3 = 5'd0;
        WD3 = 32'hDEADBEEF;
        Address1 = 5'd0;
        #20;
        $display("%0t\t%b\t%b\t%2d\t%2d\t%2d\t%08x\t%08x\t%08x\tR0 Write", 
                 $time, rst, WriteEnable3, Address1, Address2, Address3, WD3, RD1, RD2);
        
        if (RD1 == 32'h0) begin
            $display("✓ PASS: Register 0 remains 0 (write ignored)");
        end else begin
            $display("✗ FAIL: Register 0 should always be 0, got %08x", RD1);
            test_passed = 0;
        end
        test_count = test_count + 1;
        
        // Test 3: Write and read from various registers
        $display("\n--- Test 3: Basic Write/Read Operations ---");
        
        // Write to register 5
        WriteEnable3 = 1;
        Address3 = 5'd5;
        WD3 = 32'h12345678;
        @(posedge clk); // Wait for write to complete
        #1; // Small delay after clock edge
        Address1 = 5'd5; // Read from register 5
        #1;
        $display("%0t\t%b\t%b\t%2d\t%2d\t%2d\t%08x\t%08x\t%08x\tWrite R5", 
                 $time, rst, WriteEnable3, Address1, Address2, Address3, WD3, RD1, RD2);
        
        if (RD1 == 32'h12345678) begin
            $display("✓ PASS: Write/Read register 5 works");
        end else begin
            $display("✗ FAIL: Expected %08x, got %08x", 32'h12345678, RD1);
            test_passed = 0;
        end
        test_count = test_count + 1;
        
        // Write to register 10
        Address3 = 5'd10;
        WD3 = 32'hABCDEF00;
        @(posedge clk); // Wait for write to complete
        #1;
        Address2 = 5'd10; // Read from register 10
        #1;
        $display("%0t\t%b\t%b\t%2d\t%2d\t%2d\t%08x\t%08x\t%08x\tWrite R10", 
                 $time, rst, WriteEnable3, Address1, Address2, Address3, WD3, RD1, RD2);
        
        if (RD2 == 32'hABCDEF00) begin
            $display("✓ PASS: Write/Read register 10 works");
        end else begin
            $display("✗ FAIL: Expected %08x, got %08x", 32'hABCDEF00, RD2);
            test_passed = 0;
        end
        test_count = test_count + 1;
        
        // Test 4: Simultaneous dual read
        $display("\n--- Test 4: Dual Port Read ---");
        Address1 = 5'd5;  // Should read 0x12345678
        Address2 = 5'd10; // Should read 0xABCDEF00
        WriteEnable3 = 0; // Disable write
        #10;
        $display("%0t\t%b\t%b\t%2d\t%2d\t%2d\t%08x\t%08x\t%08x\tDual Read", 
                 $time, rst, WriteEnable3, Address1, Address2, Address3, WD3, RD1, RD2);
        
        if (RD1 == 32'h12345678 && RD2 == 32'hABCDEF00) begin
            $display("✓ PASS: Dual port read works correctly");
        end else begin
            $display("✗ FAIL: Dual read failed. RD1=%08x (exp:12345678), RD2=%08x (exp:ABCDEF00)", RD1, RD2);
            test_passed = 0;
        end
        test_count = test_count + 1;
        
        // Test 5: Write enable control
        $display("\n--- Test 5: Write Enable Control ---");
        WriteEnable3 = 0; // Disable write
        Address3 = 5'd15;
        WD3 = 32'hFFFFFFFF;
        @(posedge clk);
        #1;
        Address1 = 5'd15; // Read from register 15 (should be 0)
        #1;
        $display("%0t\t%b\t%b\t%2d\t%2d\t%2d\t%08x\t%08x\t%08x\tWE=0", 
                 $time, rst, WriteEnable3, Address1, Address2, Address3, WD3, RD1, RD2);
        
        if (RD1 == 32'h0) begin
            $display("✓ PASS: Write disabled when WE=0");
        end else begin
            $display("✗ FAIL: Write should be disabled when WE=0, got %08x", RD1);
            test_passed = 0;
        end
        test_count = test_count + 1;
        
        // Test 6: All registers (boundary test)
        $display("\n--- Test 6: Boundary Registers (R1 and R31) ---");
        WriteEnable3 = 1;
        
        // Test register 1
        Address3 = 5'd1;
        WD3 = 32'h11111111;
        @(posedge clk);
        #1;
        Address1 = 5'd1;
        #1;
        if (RD1 == 32'h11111111) begin
            $display("✓ PASS: Register 1 write/read works");
        end else begin
            $display("✗ FAIL: Register 1 failed. Expected 11111111, got %08x", RD1);
            test_passed = 0;
        end
        
        // Test register 31
        Address3 = 5'd31;
        WD3 = 32'h31313131;
        @(posedge clk);
        #1;
        Address2 = 5'd31;
        #1;
        $display("%0t\t%b\t%b\t%2d\t%2d\t%2d\t%08x\t%08x\t%08x\tR31 Write", 
                 $time, rst, WriteEnable3, Address1, Address2, Address3, WD3, RD1, RD2);
        
        if (RD2 == 32'h31313131) begin
            $display("✓ PASS: Register 31 write/read works");
        end else begin
            $display("✗ FAIL: Register 31 failed. Expected 31313131, got %08x", RD2);
            test_passed = 0;
        end
        test_count = test_count + 1;
        
        // Test 7: Overwrite existing data
        $display("\n--- Test 7: Data Overwrite ---");
        Address3 = 5'd5; // Overwrite register 5
        WD3 = 32'hCAFEBABE;
        @(posedge clk);
        #1;
        Address1 = 5'd5;
        #1;
        $display("%0t\t%b\t%b\t%2d\t%2d\t%2d\t%08x\t%08x\t%08x\tOverwrite", 
                 $time, rst, WriteEnable3, Address1, Address2, Address3, WD3, RD1, RD2);
        
        if (RD1 == 32'hCAFEBABE) begin
            $display("✓ PASS: Data overwrite works");
        end else begin
            $display("✗ FAIL: Overwrite failed. Expected CAFEBABE, got %08x", RD1);
            test_passed = 0;
        end
        test_count = test_count + 1;
        
        // Test 8: Reset after writes
        $display("\n--- Test 8: Reset After Operations ---");
        
        // First show what we currently have
        Address1 = 5'd5; Address2 = 5'd10; WriteEnable3 = 0; #1;
        $display("Before reset: R5=%08x, R10=%08x", RD1, RD2);
        
        // Apply reset
        rst = 0; // Active low reset
        @(posedge clk); // Reset happens on this clock edge
        #1;
        $display("After reset clock: R5=%08x, R10=%08x", RD1, RD2);
        
        // Release reset  
        rst = 1; #1;
        $display("After releasing reset: R5=%08x, R10=%08x", RD1, RD2);
        
        $display("%0t\t%b\t%b\t%2d\t%2d\t%2d\t%08x\t%08x\t%08x\tPost-Reset", 
                 $time, rst, WriteEnable3, Address1, Address2, Address3, WD3, RD1, RD2);
        
        if (RD1 == 32'h0 && RD2 == 32'h0) begin
            $display("✓ PASS: Reset clears all previous data");
        end else begin
            $display("✗ FAIL: Reset should clear all data. RD1=%08x, RD2=%08x", RD1, RD2);
            test_passed = 0;
        end
        test_count = test_count + 1;
        
        // Final results
        $display("\n=== Register_File Testbench Complete ===");
        if (test_passed) begin
            $display("🎉 ALL TESTS PASSED! (%0d/%0d)", test_count, test_count);
        end else begin
            $display("❌ SOME TESTS FAILED!");
        end
        
        #50;
        $finish;
    end

endmodule

testbench/Register_File_tb.vcd
$date
	Fri Dec  5 20:14:52 2025
$end
$version
	Icarus Verilog
$end
$timescale
	1ps
$end
$scope module Register_File_tb $end
$var wire 32 ! RD2 [31:0] $end
$var wire 32 " RD1 [31:0] $end
$var reg 5 # Address1 [4:0] $end
$var reg 5 $ Address2 [4:0] $end
$var reg 5 % Address3 [4:0] $end
$var reg 32 & WD3 [31:0] $end
$var reg 1 ' WriteEnable3 $end
$var reg 1 ( clk $end
$var reg 1 ) rst $end
$var reg 1 * test_passed $end
$var integer 32 + test_count [31:0] $end
$scope module uut $end
$var wire 5 , Address1 [4:0] $end
$var wire 5 - Address2 [4:0] $end
$var wire 5 . Address3 [4:0] $end
$var wire 32 / RD1 [31:0] $end
$var wire 32 0 RD2 [31:0] $end
$var wire 32 1 WD3 [31:0] $end
$var wire 1 ' WriteEnable3 $end
$var wire 1 ( clk $end
$var wire 1 ) rst $end
$var integer 32 2 i [31:0] $end
$upscope $end
$upscope $end
$enddefinitions $end
$comment Show the parameter values. $end
$dumpall
$end
#0
$dumpvars
b100000 2
b0 1
b0 0
b0 /
b0 .
b0 -
b0 ,
b0 +
1*
0)
0(
0'
b0 &
b0 %
b0 $
b0 #
b0 "
b0 !
$end
#5000
b100000 2
1(
#10000
0(
#15000
b100000 2
1(
#20000
0(
1)
b1 +
#25000
1(
#30000
0(
b11011110101011011011111011101111 &
b11011110101011011011111011101111 1
1'
#35000
1(
#40000
0(
#45000
1(
#50000
0(
b10010001101000101011001111000 &
b10010001101000101011001111000 1
b101 %
b101 .
b10 +
#55000
1(
#56000
b10010001101000101011001111000 "
b10010001101000101011001111000 /
b101 #
b101 ,
#57000
b10101011110011011110111100000000 &
b10101011110011011110111100000000 1
b1010 %
b1010 .
b11 +
#60000
0(
#65000
1(
#66000
b10101011110011011110111100000000 !
b10101011110011011110111100000000 0
b1010 $
b1010 -
#67000
0'
b100 +
#70000
0(
#75000
1(
#77000
b11111111111111111111111111111111 &
b11111111111111111111111111111111 1
b1111 %
b1111 .
b101 +
#80000
0(
#85000
1(
#86000
b0 "
b0 /
b1111 #
b1111 ,
#87000
b10001000100010001000100010001 &
b10001000100010001000100010001 1
b1 %
b1 .
1'
b110 +
#90000
0(
#95000
1(
#96000
b10001000100010001000100010001 "
b10001000100010001000100010001 /
b1 #
b1 ,
#97000
b110001001100010011000100110001 &
b110001001100010011000100110001 1
b11111 %
b11111 .
#100000
0(
#105000
1(
#106000
b110001001100010011000100110001 !
b110001001100010011000100110001 0
b11111 $
b11111 -
#107000
b11001010111111101011101010111110 &
b11001010111111101011101010111110 1
b101 %
b101 .
b111 +
#110000
0(
#115000
1(
#116000
b11001010111111101011101010111110 "
b11001010111111101011101010111110 /
b101 #
b101 ,
#117000
0'
b10101011110011011110111100000000 !
b10101011110011011110111100000000 0
b1010 $
b1010 -
b1000 +
#118000
0)
#120000
0(
#125000
b0 !
b0 0
b0 "
b0 /
b100000 2
1(
#126000
1)
#127000
b1001 +
