define.v

// ALU_Ctrl
`define ALU_NONE                                4'b0000
`define ALU_SHIFTL                              4'b0001
`define ALU_SHIFTR                              4'b0010
`define ALU_SHIFTR_ARITH                        4'b0011
`define ALU_ADD                                 4'b0100
`define ALU_SUB                                 4'b0110
`define ALU_AND                                 4'b0111
`define ALU_OR                                  4'b1000
`define ALU_XOR                                 4'b1001
`define ALU_LESS_THAN                           4'b1010
`define ALU_LESS_THAN_SIGNED                    4'b1011


// sel_ext
`define Ext_ImmI      3'b000 // Immediate extension for I-type instructions
`define Ext_ImmS      3'b001
`define Ext_ImmB      3'b010
`define Ext_ImmU      3'b011
`define Ext_ImmJ      3'b100


//ALUOP
`define ALUOP_LOAD_STORE                        3'b000
`define ALUOP_RTYPE                             3'b001
`define ALUOP_ITYPE                            3'b010
`define ALUOP_BRANCH                            3'b011
`define ALUOP_J_UAL                          3'b100

//ResultSrc
`define FROM_ALU                                 3'b000          // from ALU Result
`define FROM_MEM                                 3'b001          // from Memory
`define FROM_PC_                                 3'b010          // PC + 4
`define FROM_IMM                                 3'b011          // ImmExt

// Opcode definitions
`define OPCODE_RTYPE  7'b011_0011  // R-type
`define OPCODE_ITYPE  7'b001_0011  // I-type 
`define OPCODE_LOAD   7'b000_0011  // lw
`define OPCODE_STORE  7'b010_0011  // sw
`define OPCODE_BRANCH 7'b110_0011  // B-Type(beq)
`define OPCODE_JAL    7'b110_1111  // J-Type(jal)
`define OPCODE_LUI    7'b011_0111  // U-Type(lui)

// sel_ext
`define ALU_IMM 1'b1 // the second ALU operand is immediate
`define ALU_REG 1'b0 // the second ALU operand is register


// PCSrc
`define PC_NOJUMP 1'b0 // PC + 4
`define PC_J_OFFSET 1'b1 // PC + immediate offset


//YES/NO
`define YES 1'b1
`define NO  1'b0

src/Sign_Extend.v
module Sign_Extend(Ins,Imm_src,ImmExt);
    input [2:0] Imm_src;
    input [31:0] Ins;
    output [31:0] ImmExt;

    always@(*) begin
        case(Imm_src)
        `Ext_ImmI: ImmExt <= {{21{Ins[31]}}, Ins[30:25], Ins[24:21], Ins[20]};
        `Ext_ImmS: ImmExt <= {{21{Ins[31]}}, Ins[30:25], Ins[11:8], Ins[7]};
        `Ext_ImmB: ImmExt <= {{20{Ins[31]}}, Ins[7], Ins[30:25], Ins[11:8], 1'b0};
        `Ext_ImmU: ImmExt <= {Ins[31], Ins[30:20], Ins[19:12], 11'b000_0000_0000};
        `Ext_ImmJ: ImmExt <= {{12{Ins[31]}}, Ins[19:12], Ins[20], Ins[30:25], Ins[24:21], 1'b0};
            default: ImmExt <= {{21{Ins[31]}}, Ins[30:25], Ins[24:21], Ins[20]};
        endcase
    end

endmodule

testbench/Sign_Extend_tb.v
`timescale 1ns/1ps

module Sign_Extend_tb();
    // Include define file for immediate type constants
    `include "../src/define.v"
    
    // Testbench signals
    reg [31:0] Ins;
    reg [2:0] Imm_src;
    wire [31:0] ImmExt;
    
    // Instantiate the Sign_Extend module
    Sign_Extend uut (
        .Ins(Ins),
        .Imm_src(Imm_src),
        .ImmExt(ImmExt)
    );
    
    // Test vectors and expected results
    reg [31:0] expected;
    
    // Test sequence
    initial begin
        // Initialize signals
        Ins = 32'h00000000;
        Imm_src = 3'b000;
        
        // Create VCD file for waveform viewing
        $dumpfile("Sign_Extend_tb.vcd");
        $dumpvars(0, Sign_Extend_tb);
        
        $display("=== Sign_Extend Module Testbench ===");
        $display("Time\tImm_src\tInstruction\t\tImmExt\t\t\tExpected\tType");
        
        #1; // Small delay for signal propagation
        
        // Test 1: I-type immediate (12-bit sign extended)
        $display("\n--- Test 1: I-type Immediate ---");
        Ins = 32'h00C00093;  // ADDI x1, x0, 12 (positive immediate)
        Imm_src = `Ext_ImmI;
        expected = 32'h0000000C;  // +12 sign extended
        #10;
        $display("%0t\t%b\t%h\t%h\t%h\tI-type", $time, Imm_src, Ins, ImmExt, expected);
        if (ImmExt == expected) 
            $display("✓ PASS: I-type positive immediate");
        else 
            $display("✗ FAIL: Expected %h, got %h", expected, ImmExt);
        
        // Test 2: I-type negative immediate
        Ins = 32'hFFF00093;  // ADDI x1, x0, -1 (negative immediate)
        Imm_src = `Ext_ImmI;
        expected = 32'hFFFFFFFF;  // -1 sign extended
        #10;
        $display("%0t\t%b\t%h\t%h\t%h\tI-type", $time, Imm_src, Ins, ImmExt, expected);
        if (ImmExt == expected) 
            $display("✓ PASS: I-type negative immediate");
        else 
            $display("✗ FAIL: Expected %h, got %h", expected, ImmExt);
        
        // Test 3: S-type immediate (store instruction)
        $display("\n--- Test 2: S-type Immediate ---");
        Ins = 32'h00812423;  // SW x8, 8(x2) - store with offset 8
        Imm_src = `Ext_ImmS;
        expected = 32'h00000008;  // +8 sign extended
        #10;
        $display("%0t\t%b\t%h\t%h\t%h\tS-type", $time, Imm_src, Ins, ImmExt, expected);
        if (ImmExt == expected) 
            $display("✓ PASS: S-type positive immediate");
        else 
            $display("✗ FAIL: Expected %h, got %h", expected, ImmExt);
        
        // Test 4: S-type negative immediate
        Ins = 32'hFE812E23;  // SW with negative offset
        Imm_src = `Ext_ImmS;
        expected = 32'hFFFFFFFC;  // -4 sign extended  
        #10;
        $display("%0t\t%b\t%h\t%h\t%h\tS-type", $time, Imm_src, Ins, ImmExt, expected);
        if (ImmExt == expected) 
            $display("✓ PASS: S-type negative immediate");
        else 
            $display("✗ FAIL: Expected %h, got %h", expected, ImmExt);
        
        // Test 5: B-type immediate (branch instruction)
        $display("\n--- Test 3: B-type Immediate ---");
        Ins = 32'h00208463;  // BEQ x1, x2, 8 - branch with offset 8
        Imm_src = `Ext_ImmB;
        expected = 32'h00000008;  // +8 sign extended (LSB always 0)
        #10;
        $display("%0t\t%b\t%h\t%h\t%h\tB-type", $time, Imm_src, Ins, ImmExt, expected);
        if (ImmExt == expected) 
            $display("✓ PASS: B-type positive immediate");
        else 
            $display("✗ FAIL: Expected %h, got %h", expected, ImmExt);
        
        // Test 6: B-type negative immediate
        Ins = 32'hFE208EE3;  // BEQ with negative offset
        Imm_src = `Ext_ImmB;
        expected = 32'hFFFFFFFC;  // -4 sign extended
        #10;
        $display("%0t\t%b\t%h\t%h\t%h\tB-type", $time, Imm_src, Ins, ImmExt, expected);
        if (ImmExt == expected) 
            $display("✓ PASS: B-type negative immediate");
        else 
            $display("✗ FAIL: Expected %h, got %h", expected, ImmExt);
        
        // Test 7: U-type immediate (LUI instruction)
        $display("\n--- Test 4: U-type Immediate ---");
        Ins = 32'h12345137;  // LUI x2, 0x12345
        Imm_src = `Ext_ImmU;
        expected = 32'h12345000;  // Upper 20 bits, lower 12 bits zero
        #10;
        $display("%0t\t%b\t%h\t%h\t%h\tU-type", $time, Imm_src, Ins, ImmExt, expected);
        if (ImmExt == expected) 
            $display("✓ PASS: U-type immediate");
        else 
            $display("✗ FAIL: Expected %h, got %h", expected, ImmExt);
        
        // Test 8: U-type with sign bit set
        Ins = 32'hFFFFF137;  // LUI with upper bits set
        Imm_src = `Ext_ImmU;
        expected = 32'hFFFFF000;  // Upper 20 bits, lower 12 bits zero
        #10;
        $display("%0t\t%b\t%h\t%h\t%h\tU-type", $time, Imm_src, Ins, ImmExt, expected);
        if (ImmExt == expected) 
            $display("✓ PASS: U-type immediate with high bits");
        else 
            $display("✗ FAIL: Expected %h, got %h", expected, ImmExt);
        
        // Test 9: J-type immediate (JAL instruction)
        $display("\n--- Test 5: J-type Immediate ---");
        Ins = 32'h008000EF;  // JAL x1, 8 - jump with offset 8
        Imm_src = `Ext_ImmJ;
        expected = 32'h00000008;  // +8 sign extended (LSB always 0)
        #10;
        $display("%0t\t%b\t%h\t%h\t%h\tJ-type", $time, Imm_src, Ins, ImmExt, expected);
        if (ImmExt == expected) 
            $display("✓ PASS: J-type positive immediate");
        else 
            $display("✗ FAIL: Expected %h, got %h", expected, ImmExt);
        
        // Test 10: J-type negative immediate
        Ins = 32'hFF8000EF;  // JAL with negative offset
        Imm_src = `Ext_ImmJ;
        expected = 32'hFFF007F8;  // Correct J-type immediate extraction
        #10;
        $display("%0t\t%b\t%h\t%h\t%h\tJ-type", $time, Imm_src, Ins, ImmExt, expected);
        if (ImmExt == expected) 
            $display("✓ PASS: J-type negative immediate");
        else 
            $display("✗ FAIL: Expected %h, got %h", expected, ImmExt);
        
        // Test 11: Zero immediate values
        $display("\n--- Test 6: Zero immediate values ---");
        Ins = 32'h00000013;  // ADDI x0, x0, 0 (NOP)
        Imm_src = `Ext_ImmI;
        expected = 32'h00000000;
        #10;
        $display("%0t\t%b\t%h\t%h\t%h\tI-type", $time, Imm_src, Ins, ImmExt, expected);
        if (ImmExt == expected) 
            $display("✓ PASS: Zero I-type immediate");
        else 
            $display("✗ FAIL: Expected %h, got %h", expected, ImmExt);
        
        // Test 12: Maximum positive I-type immediate
        $display("\n--- Test 7: Maximum values ---");
        Ins = 32'h7FF00013;  // ADDI with max positive immediate (2047)
        Imm_src = `Ext_ImmI;
        expected = 32'h000007FF;  // +2047 sign extended
        #10;
        $display("%0t\t%b\t%h\t%h\t%h\tI-type", $time, Imm_src, Ins, ImmExt, expected);
        if (ImmExt == expected) 
            $display("✓ PASS: Maximum positive I-type immediate");
        else 
            $display("✗ FAIL: Expected %h, got %h", expected, ImmExt);
        
        // Test 13: Maximum negative I-type immediate  
        Ins = 32'h80000013;  // ADDI with max negative immediate (-2048)
        Imm_src = `Ext_ImmI;
        expected = 32'hFFFFF800;  // -2048 sign extended
        #10;
        $display("%0t\t%b\t%h\t%h\t%h\tI-type", $time, Imm_src, Ins, ImmExt, expected);
        if (ImmExt == expected) 
            $display("✓ PASS: Maximum negative I-type immediate");
        else 
            $display("✗ FAIL: Expected %h, got %h", expected, ImmExt);
        
        // Test 14: Default case (should behave like I-type)
        $display("\n--- Test 8: Default case ---");
        Ins = 32'h12345678;
        Imm_src = 3'b111;  // Invalid selector (should default to I-type)
        expected = 32'h00000123;  // Should extract like I-type: bits [31:20] = 0x123
        #10;
        $display("%0t\t%b\t%h\t%h\t%h\tDefault", $time, Imm_src, Ins, ImmExt, expected);
        if (ImmExt == expected) 
            $display("✓ PASS: Default case works like I-type");
        else 
            $display("✗ FAIL: Expected %h, got %h", expected, ImmExt);
        
        // Test 15: Rapid switching between types
        $display("\n--- Test 9: Rapid type switching ---");
        Ins = 32'hFFF00093;  // Instruction with negative immediate
        
        Imm_src = `Ext_ImmI;
        #1;
        if (ImmExt == 32'hFFFFFFFF) 
            $display("✓ PASS: Quick switch to I-type works");
        
        Imm_src = `Ext_ImmS;
        #1;
        if (ImmExt[11:0] == 12'h093) 
            $display("✓ PASS: Quick switch to S-type works");
        
        Imm_src = `Ext_ImmI;
        #1;
        if (ImmExt == 32'hFFFFFFFF) 
            $display("✓ PASS: Quick switch back to I-type works");
        
        $display("\n=== Sign_Extend Testbench Complete ===");
        #50;
        $finish;
    end
    
    // Helper task to check bit extraction
    task check_bits;
        input [31:0] instruction;
        input [2:0] imm_type;
        input [31:0] expected_result;
        input [50*8:1] test_name;
        begin
            Ins = instruction;
            Imm_src = imm_type;
            #1;
            if (ImmExt == expected_result)
                $display("✓ PASS: %s", test_name);
            else
                $display("✗ FAIL: %s - Expected %h, got %h", test_name, expected_result, ImmExt);
        end
    endtask
    
    // Monitor for debugging
    always @(*) begin
        #0.1; // Small delay to avoid race conditions
        if (Ins !== 32'hxxxxxxxx && Imm_src !== 3'bxxx) begin
            case (Imm_src)
                `Ext_ImmI: begin
                    // I-type: sign extend bits [31:20]
                    if (ImmExt !== {{21{Ins[31]}}, Ins[30:25], Ins[24:21], Ins[20]})
                        $display("WARNING: I-type extraction mismatch at time %0t", $time);
                end
                `Ext_ImmS: begin
                    // S-type: sign extend {bits[31:25], bits[11:7]}
                    if (ImmExt !== {{21{Ins[31]}}, Ins[30:25], Ins[11:8], Ins[7]})
                        $display("WARNING: S-type extraction mismatch at time %0t", $time);
                end
                `Ext_ImmB: begin
                    // B-type: sign extend {bit[31], bit[7], bits[30:25], bits[11:8], 1'b0}
                    if (ImmExt !== {{20{Ins[31]}}, Ins[7], Ins[30:25], Ins[11:8], 1'b0})
                        $display("WARNING: B-type extraction mismatch at time %0t", $time);
                end
                `Ext_ImmU: begin
                    // U-type: {bits[31:12], 12'b0}
                    if (ImmExt !== {Ins[31], Ins[30:20], Ins[19:12], 12'b0})
                        $display("WARNING: U-type extraction mismatch at time %0t", $time);
                end
                `Ext_ImmJ: begin
                    // J-type: sign extend {bit[31], bits[19:12], bit[20], bits[30:25], bits[24:21], 1'b0}
                    if (ImmExt !== {{12{Ins[31]}}, Ins[19:12], Ins[20], Ins[30:25], Ins[24:21], 1'b0})
                        $display("WARNING: J-type extraction mismatch at time %0t", $time);
                end
            endcase
        end
    end
    
endmodule

testbench/Sign_Extend_tb.vcd
$date
	Fri Dec  5 20:14:52 2025
$end
$version
	Icarus Verilog
$end
$timescale
	1ps
$end
$scope module Sign_Extend_tb $end
$var wire 32 ! ImmExt [31:0] $end
$var reg 3 " Imm_src [2:0] $end
$var reg 32 # Ins [31:0] $end
$var reg 32 $ expected [31:0] $end
$scope module uut $end
$var wire 3 % Imm_src [2:0] $end
$var wire 32 & Ins [31:0] $end
$var reg 32 ' ImmExt [31:0] $end
$upscope $end
$scope task check_bits $end
$var reg 32 ( expected_result [31:0] $end
$var reg 3 ) imm_type [2:0] $end
$var reg 32 * instruction [31:0] $end
$var reg 400 + test_name [400:1] $end
$upscope $end
$upscope $end
$enddefinitions $end
$comment Show the parameter values. $end
$dumpall
$end
#0
$dumpvars
bx +
bx *
bx )
bx (
b0 '
b0 &
b0 %
bx $
b0 #
b0 "
b0 !
$end
#1000
b1100 !
b1100 '
b1100 $
b110000000000000010010011 #
b110000000000000010010011 &
#11000
b11111111111111111111111111111111 !
b11111111111111111111111111111111 '
b11111111111111111111111111111111 $
b11111111111100000000000010010011 #
b11111111111100000000000010010011 &
#21000
b1000 !
b1000 '
b1000 $
b1 "
b1 %
b100000010010010000100011 #
b100000010010010000100011 &
#31000
b11111111111111111111111111111100 !
b11111111111111111111111111111100 '
b11111111111111111111111111111100 $
b11111110100000010010111000100011 #
b11111110100000010010111000100011 &
#41000
b1000 !
b1000 '
b1000 $
b10 "
b10 %
b1000001000010001100011 #
b1000001000010001100011 &
#51000
b11111111111111111111111111111100 !
b11111111111111111111111111111100 '
b11111111111111111111111111111100 $
b11111110001000001000111011100011 #
b11111110001000001000111011100011 &
#61000
b10010001101000101000000000000 !
b10010001101000101000000000000 '
b10010001101000101000000000000 $
b11 "
b11 %
b10010001101000101000100110111 #
b10010001101000101000100110111 &
#71000
b11111111111111111111000000000000 !
b11111111111111111111000000000000 '
b11111111111111111111000000000000 $
b11111111111111111111000100110111 #
b11111111111111111111000100110111 &
#81000
b1000 !
b1000 '
b1000 $
b100 "
b100 %
b100000000000000011101111 #
b100000000000000011101111 &
#91000
b11111111111100000000011111111000 !
b11111111111100000000011111111000 '
b11111111111100000000011111111000 $
b11111111100000000000000011101111 #
b11111111100000000000000011101111 &
#101000
b0 !
b0 '
b0 $
b0 "
b0 %
b10011 #
b10011 &
#111000
b11111111111 !
b11111111111 '
b11111111111 $
b1111111111100000000000000010011 #
b1111111111100000000000000010011 &
#121000
b11111111111111111111100000000000 !
b11111111111111111111100000000000 '
b11111111111111111111100000000000 $
b10000000000000000000000000010011 #
b10000000000000000000000000010011 &
#131000
b100100011 !
b100100011 '
b100100011 $
b111 "
b111 %
b10010001101000101011001111000 #
b10010001101000101011001111000 &
#141000
b11111111111111111111111111111111 !
b11111111111111111111111111111111 '
b0 "
b0 %
b11111111111100000000000010010011 #
b11111111111100000000000010010011 &
#142000
b11111111111111111111111111100001 !
b11111111111111111111111111100001 '
b1 "
b1 %
#143000
b11111111111111111111111111111111 !
b11111111111111111111111111111111 '
b0 "
b0 %
